<?xml version="1.0" encoding="UTF-8"?>
<questestinterop xmlns="http://www.imsglobal.org/xsd/ims_qtiasiv1p2"
xmlns:xsi="http://www.w3.org/2001/XMLSchema-instance" xsi:schemaLocation="http://www.imsglobal.org/xsd/ims_qtiasiv1p2 http://www.imsglobal.org/profile/cc/ccv1p3/ccv1p3_qtiasiv1p2p1_v1p0.xsd">
  <objectbank ident="QDB_1">
      <item ident="QUE_pool4007_1" title="CH-3 Network Traffic Signatures 1">
        <itemmetadata>
          <qtimetadata>
            <qtimetadatafield>
              <fieldlabel>cc_profile</fieldlabel>
              <fieldentry>cc.true_false.v0p1</fieldentry>
            </qtimetadatafield>
          </qtimetadata>
        </itemmetadata>
        <presentation>
          <material>
            <mattext texttype="text/html">All devices interpret attack signatures uniformly.</mattext>
          </material>
          <response_lid ident="QUE_pool4007_1_RL" rcardinality="Single">
            <render_choice>
              <response_label ident="true">
                <material>
                  <mattext texttype="text/html">true</mattext>
                </material>
              </response_label>
              <response_label ident="false">
                <material>
                  <mattext texttype="text/html">false</mattext>
                </material>
              </response_label>
            </render_choice>
          </response_lid>
        </presentation>
        <resprocessing>
          <outcomes>
            <decvar maxvalue="1.0" minvalue="0" varname="SCORE" vartype="Decimal"/>
          </outcomes>
          <respcondition continue="No">
            <conditionvar>
              <varequal case="Yes" respident="QUE_pool4007_1_RL">false</varequal>
            </conditionvar>
            <setvar action="Set" varname="SCORE">100</setvar>
          </respcondition>
        </resprocessing>
      </item>
      <item ident="QUE_pool4007_2" title="CH-3 Network Traffic Signatures 2">
        <itemmetadata>
          <qtimetadata>
            <qtimetadatafield>
              <fieldlabel>cc_profile</fieldlabel>
              <fieldentry>cc.true_false.v0p1</fieldentry>
            </qtimetadatafield>
          </qtimetadata>
        </itemmetadata>
        <presentation>
          <material>
            <mattext texttype="text/html">An atomic attack is a barrage of hundreds of packets directed at a host.</mattext>
          </material>
          <response_lid ident="QUE_pool4007_2_RL" rcardinality="Single">
            <render_choice>
              <response_label ident="true">
                <material>
                  <mattext texttype="text/html">true</mattext>
                </material>
              </response_label>
              <response_label ident="false">
                <material>
                  <mattext texttype="text/html">false</mattext>
                </material>
              </response_label>
            </render_choice>
          </response_lid>
        </presentation>
        <resprocessing>
          <outcomes>
            <decvar maxvalue="1.0" minvalue="0" varname="SCORE" vartype="Decimal"/>
          </outcomes>
          <respcondition continue="No">
            <conditionvar>
              <varequal case="Yes" respident="QUE_pool4007_2_RL">false</varequal>
            </conditionvar>
            <setvar action="Set" varname="SCORE">100</setvar>
          </respcondition>
        </resprocessing>
      </item>
      <item ident="QUE_pool4007_3" title="CH-3 Network Traffic Signatures 3">
        <itemmetadata>
          <qtimetadata>
            <qtimetadatafield>
              <fieldlabel>cc_profile</fieldlabel>
              <fieldentry>cc.true_false.v0p1</fieldentry>
            </qtimetadatafield>
          </qtimetadata>
        </itemmetadata>
        <presentation>
          <material>
            <mattext texttype="text/html">The signature of a normal FTP connection includes a three-way handshake.</mattext>
          </material>
          <response_lid ident="QUE_pool4007_3_RL" rcardinality="Single">
            <render_choice>
              <response_label ident="true">
                <material>
                  <mattext texttype="text/html">true</mattext>
                </material>
              </response_label>
              <response_label ident="false">
                <material>
                  <mattext texttype="text/html">false</mattext>
                </material>
              </response_label>
            </render_choice>
          </response_lid>
        </presentation>
        <resprocessing>
          <outcomes>
            <decvar maxvalue="1.0" minvalue="0" varname="SCORE" vartype="Decimal"/>
          </outcomes>
          <respcondition continue="No">
            <conditionvar>
              <varequal case="Yes" respident="QUE_pool4007_3_RL">true</varequal>
            </conditionvar>
            <setvar action="Set" varname="SCORE">100</setvar>
          </respcondition>
        </resprocessing>
      </item>
      <item ident="QUE_pool4007_4" title="CH-3 Network Traffic Signatures 4">
        <itemmetadata>
          <qtimetadata>
            <qtimetadatafield>
              <fieldlabel>cc_profile</fieldlabel>
              <fieldentry>cc.true_false.v0p1</fieldentry>
            </qtimetadatafield>
          </qtimetadata>
        </itemmetadata>
        <presentation>
          <material>
            <mattext texttype="text/html">Newer Trojans listen at a predetermined port on the target computer so that detection is more difficult.</mattext>
          </material>
          <response_lid ident="QUE_pool4007_4_RL" rcardinality="Single">
            <render_choice>
              <response_label ident="true">
                <material>
                  <mattext texttype="text/html">true</mattext>
                </material>
              </response_label>
              <response_label ident="false">
                <material>
                  <mattext texttype="text/html">false</mattext>
                </material>
              </response_label>
            </render_choice>
          </response_lid>
        </presentation>
        <resprocessing>
          <outcomes>
            <decvar maxvalue="1.0" minvalue="0" varname="SCORE" vartype="Decimal"/>
          </outcomes>
          <respcondition continue="No">
            <conditionvar>
              <varequal case="Yes" respident="QUE_pool4007_4_RL">false</varequal>
            </conditionvar>
            <setvar action="Set" varname="SCORE">100</setvar>
          </respcondition>
        </resprocessing>
      </item>
      <item ident="QUE_pool4007_5" title="CH-3 Network Traffic Signatures 5">
        <itemmetadata>
          <qtimetadata>
            <qtimetadatafield>
              <fieldlabel>cc_profile</fieldlabel>
              <fieldentry>cc.true_false.v0p1</fieldentry>
            </qtimetadatafield>
          </qtimetadata>
        </itemmetadata>
        <presentation>
          <material>
            <mattext texttype="text/html">Packet fragmentation is not normal, and can only occur if an attack has been initiated.</mattext>
          </material>
          <response_lid ident="QUE_pool4007_5_RL" rcardinality="Single">
            <render_choice>
              <response_label ident="true">
                <material>
                  <mattext texttype="text/html">true</mattext>
                </material>
              </response_label>
              <response_label ident="false">
                <material>
                  <mattext texttype="text/html">false</mattext>
                </material>
              </response_label>
            </render_choice>
          </response_lid>
        </presentation>
        <resprocessing>
          <outcomes>
            <decvar maxvalue="1.0" minvalue="0" varname="SCORE" vartype="Decimal"/>
          </outcomes>
          <respcondition continue="No">
            <conditionvar>
              <varequal case="Yes" respident="QUE_pool4007_5_RL">true</varequal>
            </conditionvar>
            <setvar action="Set" varname="SCORE">100</setvar>
          </respcondition>
        </resprocessing>
      </item>
      <item ident="QUE_pool4007_6" title="CH-3 Network Traffic Signatures 6">
        <itemmetadata>
          <qtimetadata>
            <qtimetadatafield>
              <fieldlabel>cc_profile</fieldlabel>
              <fieldentry>cc.multiple_choice.v0p1</fieldentry>
            </qtimetadatafield>
          </qtimetadata>
        </itemmetadata>
        <presentation>
          <material>
            <mattext texttype="text/html">How does the CVE standard make network security devices and tools more effective?</mattext>
          </material>
          <response_lid ident="QUE_pool4007_6_RL" rcardinality="Single">
            <render_choice>
              <response_label ident="QUE_pool4007_6_1">
                <material>
                  <mattext texttype="text/html">the layered approach makes attacks nearly impossible</mattext>
                </material>
              </response_label>
              <response_label ident="QUE_pool4007_6_2">
                <material>
                  <mattext texttype="text/html">they can share information about attack signatures</mattext>
                </material>
              </response_label>
              <response_label ident="QUE_pool4007_6_3">
                <material>
                  <mattext texttype="text/html">it requires you to use compatible devices from one vendor</mattext>
                </material>
              </response_label>
              <response_label ident="QUE_pool4007_6_4">
                <material>
                  <mattext texttype="text/html">it warns an attacker that your site is being monitored</mattext>
                </material>
              </response_label>
            </render_choice>
          </response_lid>
        </presentation>
        <resprocessing>
          <outcomes>
            <decvar maxvalue="1.0" minvalue="0" varname="SCORE" vartype="Decimal"/>
          </outcomes>
          <respcondition continue="Yes">
              <conditionvar>
                <varequal respident="QUE_pool4007_6_RL">QUE_pool4007_6_1</varequal>
              </conditionvar>
              <displayfeedback feedbacktype="Response" linkrefid="QUE_pool4007_6_1_fb" />
          </respcondition>
          <respcondition continue="Yes">
              <conditionvar>
                <varequal respident="QUE_pool4007_6_RL">QUE_pool4007_6_2</varequal>
              </conditionvar>
              <displayfeedback feedbacktype="Response" linkrefid="QUE_pool4007_6_2_fb" />
          </respcondition>
          <respcondition continue="Yes">
              <conditionvar>
                <varequal respident="QUE_pool4007_6_RL">QUE_pool4007_6_3</varequal>
              </conditionvar>
              <displayfeedback feedbacktype="Response" linkrefid="QUE_pool4007_6_3_fb" />
          </respcondition>
          <respcondition continue="Yes">
              <conditionvar>
                <varequal respident="QUE_pool4007_6_RL">QUE_pool4007_6_4</varequal>
              </conditionvar>
              <displayfeedback feedbacktype="Response" linkrefid="QUE_pool4007_6_4_fb" />
          </respcondition>
          <respcondition continue="No">
            <conditionvar>
              <varequal case="Yes" respident="QUE_pool4007_6_RL">QUE_pool4007_6_2</varequal>
            </conditionvar>
            <setvar action="Set" varname="SCORE">100</setvar>
          </respcondition>
        </resprocessing>
        <itemfeedback ident="QUE_pool4007_6_1_fb">
          <material>
            <mattext texttype="text/html"></mattext>
          </material>
        </itemfeedback>
        <itemfeedback ident="QUE_pool4007_6_2_fb">
          <material>
            <mattext texttype="text/html"></mattext>
          </material>
        </itemfeedback>
        <itemfeedback ident="QUE_pool4007_6_3_fb">
          <material>
            <mattext texttype="text/html"></mattext>
          </material>
        </itemfeedback>
        <itemfeedback ident="QUE_pool4007_6_4_fb">
          <material>
            <mattext texttype="text/html"></mattext>
          </material>
        </itemfeedback>
      </item>
      <item ident="QUE_pool4007_7" title="CH-3 Network Traffic Signatures 7">
        <itemmetadata>
          <qtimetadata>
            <qtimetadatafield>
              <fieldlabel>cc_profile</fieldlabel>
              <fieldentry>cc.multiple_choice.v0p1</fieldentry>
            </qtimetadatafield>
          </qtimetadata>
        </itemmetadata>
        <presentation>
          <material>
            <mattext texttype="text/html">Which of the following is NOT among the items of information that a CVE reference reports?</mattext>
          </material>
          <response_lid ident="QUE_pool4007_7_RL" rcardinality="Single">
            <render_choice>
              <response_label ident="QUE_pool4007_7_1">
                <material>
                  <mattext texttype="text/html">attack signature</mattext>
                </material>
              </response_label>
              <response_label ident="QUE_pool4007_7_2">
                <material>
                  <mattext texttype="text/html">name of the vulnerability</mattext>
                </material>
              </response_label>
              <response_label ident="QUE_pool4007_7_3">
                <material>
                  <mattext texttype="text/html">description of vulnerability</mattext>
                </material>
              </response_label>
              <response_label ident="QUE_pool4007_7_4">
                <material>
                  <mattext texttype="text/html">reference in other databases</mattext>
                </material>
              </response_label>
            </render_choice>
          </response_lid>
        </presentation>
        <resprocessing>
          <outcomes>
            <decvar maxvalue="1.0" minvalue="0" varname="SCORE" vartype="Decimal"/>
          </outcomes>
          <respcondition continue="Yes">
              <conditionvar>
                <varequal respident="QUE_pool4007_7_RL">QUE_pool4007_7_1</varequal>
              </conditionvar>
              <displayfeedback feedbacktype="Response" linkrefid="QUE_pool4007_7_1_fb" />
          </respcondition>
          <respcondition continue="Yes">
              <conditionvar>
                <varequal respident="QUE_pool4007_7_RL">QUE_pool4007_7_2</varequal>
              </conditionvar>
              <displayfeedback feedbacktype="Response" linkrefid="QUE_pool4007_7_2_fb" />
          </respcondition>
          <respcondition continue="Yes">
              <conditionvar>
                <varequal respident="QUE_pool4007_7_RL">QUE_pool4007_7_3</varequal>
              </conditionvar>
              <displayfeedback feedbacktype="Response" linkrefid="QUE_pool4007_7_3_fb" />
          </respcondition>
          <respcondition continue="Yes">
              <conditionvar>
                <varequal respident="QUE_pool4007_7_RL">QUE_pool4007_7_4</varequal>
              </conditionvar>
              <displayfeedback feedbacktype="Response" linkrefid="QUE_pool4007_7_4_fb" />
          </respcondition>
          <respcondition continue="No">
            <conditionvar>
              <varequal case="Yes" respident="QUE_pool4007_7_RL">QUE_pool4007_7_1</varequal>
            </conditionvar>
            <setvar action="Set" varname="SCORE">100</setvar>
          </respcondition>
        </resprocessing>
        <itemfeedback ident="QUE_pool4007_7_1_fb">
          <material>
            <mattext texttype="text/html"></mattext>
          </material>
        </itemfeedback>
        <itemfeedback ident="QUE_pool4007_7_2_fb">
          <material>
            <mattext texttype="text/html"></mattext>
          </material>
        </itemfeedback>
        <itemfeedback ident="QUE_pool4007_7_3_fb">
          <material>
            <mattext texttype="text/html"></mattext>
          </material>
        </itemfeedback>
        <itemfeedback ident="QUE_pool4007_7_4_fb">
          <material>
            <mattext texttype="text/html"></mattext>
          </material>
        </itemfeedback>
      </item>
      <item ident="QUE_pool4007_8" title="CH-3 Network Traffic Signatures 8">
        <itemmetadata>
          <qtimetadata>
            <qtimetadatafield>
              <fieldlabel>cc_profile</fieldlabel>
              <fieldentry>cc.multiple_choice.v0p1</fieldentry>
            </qtimetadatafield>
          </qtimetadata>
        </itemmetadata>
        <presentation>
          <material>
            <mattext texttype="text/html">Which of the following is an accurate set of characteristics you would find in an attack signature?</mattext>
          </material>
          <response_lid ident="QUE_pool4007_8_RL" rcardinality="Single">
            <render_choice>
              <response_label ident="QUE_pool4007_8_1">
                <material>
                  <mattext texttype="text/html">IP address, attacker’s alias, UDP options</mattext>
                </material>
              </response_label>
              <response_label ident="QUE_pool4007_8_2">
                <material>
                  <mattext texttype="text/html">protocol options, TCP ports, region of origin</mattext>
                </material>
              </response_label>
              <response_label ident="QUE_pool4007_8_3">
                <material>
                  <mattext texttype="text/html">IP address, TCP flags, port numbers</mattext>
                </material>
              </response_label>
              <response_label ident="QUE_pool4007_8_4">
                <material>
                  <mattext texttype="text/html">IP number, MAC address, TCP options</mattext>
                </material>
              </response_label>
            </render_choice>
          </response_lid>
        </presentation>
        <resprocessing>
          <outcomes>
            <decvar maxvalue="1.0" minvalue="0" varname="SCORE" vartype="Decimal"/>
          </outcomes>
          <respcondition continue="Yes">
              <conditionvar>
                <varequal respident="QUE_pool4007_8_RL">QUE_pool4007_8_1</varequal>
              </conditionvar>
              <displayfeedback feedbacktype="Response" linkrefid="QUE_pool4007_8_1_fb" />
          </respcondition>
          <respcondition continue="Yes">
              <conditionvar>
                <varequal respident="QUE_pool4007_8_RL">QUE_pool4007_8_2</varequal>
              </conditionvar>
              <displayfeedback feedbacktype="Response" linkrefid="QUE_pool4007_8_2_fb" />
          </respcondition>
          <respcondition continue="Yes">
              <conditionvar>
                <varequal respident="QUE_pool4007_8_RL">QUE_pool4007_8_3</varequal>
              </conditionvar>
              <displayfeedback feedbacktype="Response" linkrefid="QUE_pool4007_8_3_fb" />
          </respcondition>
          <respcondition continue="Yes">
              <conditionvar>
                <varequal respident="QUE_pool4007_8_RL">QUE_pool4007_8_4</varequal>
              </conditionvar>
              <displayfeedback feedbacktype="Response" linkrefid="QUE_pool4007_8_4_fb" />
          </respcondition>
          <respcondition continue="No">
            <conditionvar>
              <varequal case="Yes" respident="QUE_pool4007_8_RL">QUE_pool4007_8_3</varequal>
            </conditionvar>
            <setvar action="Set" varname="SCORE">100</setvar>
          </respcondition>
        </resprocessing>
        <itemfeedback ident="QUE_pool4007_8_1_fb">
          <material>
            <mattext texttype="text/html"></mattext>
          </material>
        </itemfeedback>
        <itemfeedback ident="QUE_pool4007_8_2_fb">
          <material>
            <mattext texttype="text/html"></mattext>
          </material>
        </itemfeedback>
        <itemfeedback ident="QUE_pool4007_8_3_fb">
          <material>
            <mattext texttype="text/html"></mattext>
          </material>
        </itemfeedback>
        <itemfeedback ident="QUE_pool4007_8_4_fb">
          <material>
            <mattext texttype="text/html"></mattext>
          </material>
        </itemfeedback>
      </item>
      <item ident="QUE_pool4007_9" title="CH-3 Network Traffic Signatures 9">
        <itemmetadata>
          <qtimetadata>
            <qtimetadatafield>
              <fieldlabel>cc_profile</fieldlabel>
              <fieldentry>cc.multiple_choice.v0p1</fieldentry>
            </qtimetadatafield>
          </qtimetadata>
        </itemmetadata>
        <presentation>
          <material>
            <mattext texttype="text/html">What is the term used when an IDPS doesn’t recognize that an attack is underway?</mattext>
          </material>
          <response_lid ident="QUE_pool4007_9_RL" rcardinality="Single">
            <render_choice>
              <response_label ident="QUE_pool4007_9_1">
                <material>
                  <mattext texttype="text/html">false negative</mattext>
                </material>
              </response_label>
              <response_label ident="QUE_pool4007_9_2">
                <material>
                  <mattext texttype="text/html">true positive</mattext>
                </material>
              </response_label>
              <response_label ident="QUE_pool4007_9_3">
                <material>
                  <mattext texttype="text/html">negative activity</mattext>
                </material>
              </response_label>
              <response_label ident="QUE_pool4007_9_4">
                <material>
                  <mattext texttype="text/html">positive signature</mattext>
                </material>
              </response_label>
            </render_choice>
          </response_lid>
        </presentation>
        <resprocessing>
          <outcomes>
            <decvar maxvalue="1.0" minvalue="0" varname="SCORE" vartype="Decimal"/>
          </outcomes>
          <respcondition continue="Yes">
              <conditionvar>
                <varequal respident="QUE_pool4007_9_RL">QUE_pool4007_9_1</varequal>
              </conditionvar>
              <displayfeedback feedbacktype="Response" linkrefid="QUE_pool4007_9_1_fb" />
          </respcondition>
          <respcondition continue="Yes">
              <conditionvar>
                <varequal respident="QUE_pool4007_9_RL">QUE_pool4007_9_2</varequal>
              </conditionvar>
              <displayfeedback feedbacktype="Response" linkrefid="QUE_pool4007_9_2_fb" />
          </respcondition>
          <respcondition continue="Yes">
              <conditionvar>
                <varequal respident="QUE_pool4007_9_RL">QUE_pool4007_9_3</varequal>
              </conditionvar>
              <displayfeedback feedbacktype="Response" linkrefid="QUE_pool4007_9_3_fb" />
          </respcondition>
          <respcondition continue="Yes">
              <conditionvar>
                <varequal respident="QUE_pool4007_9_RL">QUE_pool4007_9_4</varequal>
              </conditionvar>
              <displayfeedback feedbacktype="Response" linkrefid="QUE_pool4007_9_4_fb" />
          </respcondition>
          <respcondition continue="No">
            <conditionvar>
              <varequal case="Yes" respident="QUE_pool4007_9_RL">QUE_pool4007_9_1</varequal>
            </conditionvar>
            <setvar action="Set" varname="SCORE">100</setvar>
          </respcondition>
        </resprocessing>
        <itemfeedback ident="QUE_pool4007_9_1_fb">
          <material>
            <mattext texttype="text/html"></mattext>
          </material>
        </itemfeedback>
        <itemfeedback ident="QUE_pool4007_9_2_fb">
          <material>
            <mattext texttype="text/html"></mattext>
          </material>
        </itemfeedback>
        <itemfeedback ident="QUE_pool4007_9_3_fb">
          <material>
            <mattext texttype="text/html"></mattext>
          </material>
        </itemfeedback>
        <itemfeedback ident="QUE_pool4007_9_4_fb">
          <material>
            <mattext texttype="text/html"></mattext>
          </material>
        </itemfeedback>
      </item>
      <item ident="QUE_pool4007_10" title="CH-3 Network Traffic Signatures 10">
        <itemmetadata>
          <qtimetadata>
            <qtimetadatafield>
              <fieldlabel>cc_profile</fieldlabel>
              <fieldentry>cc.multiple_choice.v0p1</fieldentry>
            </qtimetadatafield>
          </qtimetadata>
        </itemmetadata>
        <presentation>
          <material>
            <mattext texttype="text/html">Which of the following is NOT a category of suspicious TCP/IP packet?</mattext>
          </material>
          <response_lid ident="QUE_pool4007_10_RL" rcardinality="Single">
            <render_choice>
              <response_label ident="QUE_pool4007_10_1">
                <material>
                  <mattext texttype="text/html">bad header information</mattext>
                </material>
              </response_label>
              <response_label ident="QUE_pool4007_10_2">
                <material>
                  <mattext texttype="text/html">single-packet attacks</mattext>
                </material>
              </response_label>
              <response_label ident="QUE_pool4007_10_3">
                <material>
                  <mattext texttype="text/html">suspicious data payload</mattext>
                </material>
              </response_label>
              <response_label ident="QUE_pool4007_10_4">
                <material>
                  <mattext texttype="text/html">suspicious CRC value</mattext>
                </material>
              </response_label>
            </render_choice>
          </response_lid>
        </presentation>
        <resprocessing>
          <outcomes>
            <decvar maxvalue="1.0" minvalue="0" varname="SCORE" vartype="Decimal"/>
          </outcomes>
          <respcondition continue="Yes">
              <conditionvar>
                <varequal respident="QUE_pool4007_10_RL">QUE_pool4007_10_1</varequal>
              </conditionvar>
              <displayfeedback feedbacktype="Response" linkrefid="QUE_pool4007_10_1_fb" />
          </respcondition>
          <respcondition continue="Yes">
              <conditionvar>
                <varequal respident="QUE_pool4007_10_RL">QUE_pool4007_10_2</varequal>
              </conditionvar>
              <displayfeedback feedbacktype="Response" linkrefid="QUE_pool4007_10_2_fb" />
          </respcondition>
          <respcondition continue="Yes">
              <conditionvar>
                <varequal respident="QUE_pool4007_10_RL">QUE_pool4007_10_3</varequal>
              </conditionvar>
              <displayfeedback feedbacktype="Response" linkrefid="QUE_pool4007_10_3_fb" />
          </respcondition>
          <respcondition continue="Yes">
              <conditionvar>
                <varequal respident="QUE_pool4007_10_RL">QUE_pool4007_10_4</varequal>
              </conditionvar>
              <displayfeedback feedbacktype="Response" linkrefid="QUE_pool4007_10_4_fb" />
          </respcondition>
          <respcondition continue="No">
            <conditionvar>
              <varequal case="Yes" respident="QUE_pool4007_10_RL">QUE_pool4007_10_4</varequal>
            </conditionvar>
            <setvar action="Set" varname="SCORE">100</setvar>
          </respcondition>
        </resprocessing>
        <itemfeedback ident="QUE_pool4007_10_1_fb">
          <material>
            <mattext texttype="text/html"></mattext>
          </material>
        </itemfeedback>
        <itemfeedback ident="QUE_pool4007_10_2_fb">
          <material>
            <mattext texttype="text/html"></mattext>
          </material>
        </itemfeedback>
        <itemfeedback ident="QUE_pool4007_10_3_fb">
          <material>
            <mattext texttype="text/html"></mattext>
          </material>
        </itemfeedback>
        <itemfeedback ident="QUE_pool4007_10_4_fb">
          <material>
            <mattext texttype="text/html"></mattext>
          </material>
        </itemfeedback>
      </item>
      <item ident="QUE_pool4007_11" title="CH-3 Network Traffic Signatures 11">
        <itemmetadata>
          <qtimetadata>
            <qtimetadatafield>
              <fieldlabel>cc_profile</fieldlabel>
              <fieldentry>cc.multiple_choice.v0p1</fieldentry>
            </qtimetadatafield>
          </qtimetadata>
        </itemmetadata>
        <presentation>
          <material>
            <mattext texttype="text/html">What can an IDPS check to try to determine whether a packet has been tampered with or damaged in transit?</mattext>
          </material>
          <response_lid ident="QUE_pool4007_11_RL" rcardinality="Single">
            <render_choice>
              <response_label ident="QUE_pool4007_11_1">
                <material>
                  <mattext texttype="text/html">parity bit</mattext>
                </material>
              </response_label>
              <response_label ident="QUE_pool4007_11_2">
                <material>
                  <mattext texttype="text/html">CRC value</mattext>
                </material>
              </response_label>
              <response_label ident="QUE_pool4007_11_3">
                <material>
                  <mattext texttype="text/html">Checksum</mattext>
                </material>
              </response_label>
              <response_label ident="QUE_pool4007_11_4">
                <material>
                  <mattext texttype="text/html">fragment offset</mattext>
                </material>
              </response_label>
            </render_choice>
          </response_lid>
        </presentation>
        <resprocessing>
          <outcomes>
            <decvar maxvalue="1.0" minvalue="0" varname="SCORE" vartype="Decimal"/>
          </outcomes>
          <respcondition continue="Yes">
              <conditionvar>
                <varequal respident="QUE_pool4007_11_RL">QUE_pool4007_11_1</varequal>
              </conditionvar>
              <displayfeedback feedbacktype="Response" linkrefid="QUE_pool4007_11_1_fb" />
          </respcondition>
          <respcondition continue="Yes">
              <conditionvar>
                <varequal respident="QUE_pool4007_11_RL">QUE_pool4007_11_2</varequal>
              </conditionvar>
              <displayfeedback feedbacktype="Response" linkrefid="QUE_pool4007_11_2_fb" />
          </respcondition>
          <respcondition continue="Yes">
              <conditionvar>
                <varequal respident="QUE_pool4007_11_RL">QUE_pool4007_11_3</varequal>
              </conditionvar>
              <displayfeedback feedbacktype="Response" linkrefid="QUE_pool4007_11_3_fb" />
          </respcondition>
          <respcondition continue="Yes">
              <conditionvar>
                <varequal respident="QUE_pool4007_11_RL">QUE_pool4007_11_4</varequal>
              </conditionvar>
              <displayfeedback feedbacktype="Response" linkrefid="QUE_pool4007_11_4_fb" />
          </respcondition>
          <respcondition continue="No">
            <conditionvar>
              <varequal case="Yes" respident="QUE_pool4007_11_RL">QUE_pool4007_11_3</varequal>
            </conditionvar>
            <setvar action="Set" varname="SCORE">100</setvar>
          </respcondition>
        </resprocessing>
        <itemfeedback ident="QUE_pool4007_11_1_fb">
          <material>
            <mattext texttype="text/html"></mattext>
          </material>
        </itemfeedback>
        <itemfeedback ident="QUE_pool4007_11_2_fb">
          <material>
            <mattext texttype="text/html"></mattext>
          </material>
        </itemfeedback>
        <itemfeedback ident="QUE_pool4007_11_3_fb">
          <material>
            <mattext texttype="text/html"></mattext>
          </material>
        </itemfeedback>
        <itemfeedback ident="QUE_pool4007_11_4_fb">
          <material>
            <mattext texttype="text/html"></mattext>
          </material>
        </itemfeedback>
      </item>
      <item ident="QUE_pool4007_12" title="CH-3 Network Traffic Signatures 12">
        <itemmetadata>
          <qtimetadata>
            <qtimetadatafield>
              <fieldlabel>cc_profile</fieldlabel>
              <fieldentry>cc.multiple_choice.v0p1</fieldentry>
            </qtimetadatafield>
          </qtimetadata>
        </itemmetadata>
        <presentation>
          <material>
            <mattext texttype="text/html">What type of attack does a remote-access Trojan attempt to perpetrate?</mattext>
          </material>
          <response_lid ident="QUE_pool4007_12_RL" rcardinality="Single">
            <render_choice>
              <response_label ident="QUE_pool4007_12_1">
                <material>
                  <mattext texttype="text/html">Worm</mattext>
                </material>
              </response_label>
              <response_label ident="QUE_pool4007_12_2">
                <material>
                  <mattext texttype="text/html">back door</mattext>
                </material>
              </response_label>
              <response_label ident="QUE_pool4007_12_3">
                <material>
                  <mattext texttype="text/html">remote denial of service</mattext>
                </material>
              </response_label>
              <response_label ident="QUE_pool4007_12_4">
                <material>
                  <mattext texttype="text/html">composite attack</mattext>
                </material>
              </response_label>
            </render_choice>
          </response_lid>
        </presentation>
        <resprocessing>
          <outcomes>
            <decvar maxvalue="1.0" minvalue="0" varname="SCORE" vartype="Decimal"/>
          </outcomes>
          <respcondition continue="Yes">
              <conditionvar>
                <varequal respident="QUE_pool4007_12_RL">QUE_pool4007_12_1</varequal>
              </conditionvar>
              <displayfeedback feedbacktype="Response" linkrefid="QUE_pool4007_12_1_fb" />
          </respcondition>
          <respcondition continue="Yes">
              <conditionvar>
                <varequal respident="QUE_pool4007_12_RL">QUE_pool4007_12_2</varequal>
              </conditionvar>
              <displayfeedback feedbacktype="Response" linkrefid="QUE_pool4007_12_2_fb" />
          </respcondition>
          <respcondition continue="Yes">
              <conditionvar>
                <varequal respident="QUE_pool4007_12_RL">QUE_pool4007_12_3</varequal>
              </conditionvar>
              <displayfeedback feedbacktype="Response" linkrefid="QUE_pool4007_12_3_fb" />
          </respcondition>
          <respcondition continue="Yes">
              <conditionvar>
                <varequal respident="QUE_pool4007_12_RL">QUE_pool4007_12_4</varequal>
              </conditionvar>
              <displayfeedback feedbacktype="Response" linkrefid="QUE_pool4007_12_4_fb" />
          </respcondition>
          <respcondition continue="No">
            <conditionvar>
              <varequal case="Yes" respident="QUE_pool4007_12_RL">QUE_pool4007_12_2</varequal>
            </conditionvar>
            <setvar action="Set" varname="SCORE">100</setvar>
          </respcondition>
        </resprocessing>
        <itemfeedback ident="QUE_pool4007_12_1_fb">
          <material>
            <mattext texttype="text/html"></mattext>
          </material>
        </itemfeedback>
        <itemfeedback ident="QUE_pool4007_12_2_fb">
          <material>
            <mattext texttype="text/html"></mattext>
          </material>
        </itemfeedback>
        <itemfeedback ident="QUE_pool4007_12_3_fb">
          <material>
            <mattext texttype="text/html"></mattext>
          </material>
        </itemfeedback>
        <itemfeedback ident="QUE_pool4007_12_4_fb">
          <material>
            <mattext texttype="text/html"></mattext>
          </material>
        </itemfeedback>
      </item>
      <item ident="QUE_pool4007_13" title="CH-3 Network Traffic Signatures 13">
        <itemmetadata>
          <qtimetadata>
            <qtimetadatafield>
              <fieldlabel>cc_profile</fieldlabel>
              <fieldentry>cc.multiple_choice.v0p1</fieldentry>
            </qtimetadatafield>
          </qtimetadata>
        </itemmetadata>
        <presentation>
          <material>
            <mattext texttype="text/html">Under which attack category does a UNIX Sendmail exploitation fall?</mattext>
          </material>
          <response_lid ident="QUE_pool4007_13_RL" rcardinality="Single">
            <render_choice>
              <response_label ident="QUE_pool4007_13_1">
                <material>
                  <mattext texttype="text/html">bad header information</mattext>
                </material>
              </response_label>
              <response_label ident="QUE_pool4007_13_2">
                <material>
                  <mattext texttype="text/html">single-packet attack</mattext>
                </material>
              </response_label>
              <response_label ident="QUE_pool4007_13_3">
                <material>
                  <mattext texttype="text/html">multiple-packet attack</mattext>
                </material>
              </response_label>
              <response_label ident="QUE_pool4007_13_4">
                <material>
                  <mattext texttype="text/html">suspicious data payload</mattext>
                </material>
              </response_label>
            </render_choice>
          </response_lid>
        </presentation>
        <resprocessing>
          <outcomes>
            <decvar maxvalue="1.0" minvalue="0" varname="SCORE" vartype="Decimal"/>
          </outcomes>
          <respcondition continue="Yes">
              <conditionvar>
                <varequal respident="QUE_pool4007_13_RL">QUE_pool4007_13_1</varequal>
              </conditionvar>
              <displayfeedback feedbacktype="Response" linkrefid="QUE_pool4007_13_1_fb" />
          </respcondition>
          <respcondition continue="Yes">
              <conditionvar>
                <varequal respident="QUE_pool4007_13_RL">QUE_pool4007_13_2</varequal>
              </conditionvar>
              <displayfeedback feedbacktype="Response" linkrefid="QUE_pool4007_13_2_fb" />
          </respcondition>
          <respcondition continue="Yes">
              <conditionvar>
                <varequal respident="QUE_pool4007_13_RL">QUE_pool4007_13_3</varequal>
              </conditionvar>
              <displayfeedback feedbacktype="Response" linkrefid="QUE_pool4007_13_3_fb" />
          </respcondition>
          <respcondition continue="Yes">
              <conditionvar>
                <varequal respident="QUE_pool4007_13_RL">QUE_pool4007_13_4</varequal>
              </conditionvar>
              <displayfeedback feedbacktype="Response" linkrefid="QUE_pool4007_13_4_fb" />
          </respcondition>
          <respcondition continue="No">
            <conditionvar>
              <varequal case="Yes" respident="QUE_pool4007_13_RL">QUE_pool4007_13_4</varequal>
            </conditionvar>
            <setvar action="Set" varname="SCORE">100</setvar>
          </respcondition>
        </resprocessing>
        <itemfeedback ident="QUE_pool4007_13_1_fb">
          <material>
            <mattext texttype="text/html"></mattext>
          </material>
        </itemfeedback>
        <itemfeedback ident="QUE_pool4007_13_2_fb">
          <material>
            <mattext texttype="text/html"></mattext>
          </material>
        </itemfeedback>
        <itemfeedback ident="QUE_pool4007_13_3_fb">
          <material>
            <mattext texttype="text/html"></mattext>
          </material>
        </itemfeedback>
        <itemfeedback ident="QUE_pool4007_13_4_fb">
          <material>
            <mattext texttype="text/html"></mattext>
          </material>
        </itemfeedback>
      </item>
      <item ident="QUE_pool4007_14" title="CH-3 Network Traffic Signatures 14">
        <itemmetadata>
          <qtimetadata>
            <qtimetadatafield>
              <fieldlabel>cc_profile</fieldlabel>
              <fieldentry>cc.multiple_choice.v0p1</fieldentry>
            </qtimetadatafield>
          </qtimetadata>
        </itemmetadata>
        <presentation>
          <material>
            <mattext texttype="text/html">Of what category of attack is a DoS attack an example?</mattext>
          </material>
          <response_lid ident="QUE_pool4007_14_RL" rcardinality="Single">
            <render_choice>
              <response_label ident="QUE_pool4007_14_1">
                <material>
                  <mattext texttype="text/html">bad header information</mattext>
                </material>
              </response_label>
              <response_label ident="QUE_pool4007_14_2">
                <material>
                  <mattext texttype="text/html">single-packet attack</mattext>
                </material>
              </response_label>
              <response_label ident="QUE_pool4007_14_3">
                <material>
                  <mattext texttype="text/html">multiple-packet attack</mattext>
                </material>
              </response_label>
              <response_label ident="QUE_pool4007_14_4">
                <material>
                  <mattext texttype="text/html">suspicious data payload</mattext>
                </material>
              </response_label>
            </render_choice>
          </response_lid>
        </presentation>
        <resprocessing>
          <outcomes>
            <decvar maxvalue="1.0" minvalue="0" varname="SCORE" vartype="Decimal"/>
          </outcomes>
          <respcondition continue="Yes">
              <conditionvar>
                <varequal respident="QUE_pool4007_14_RL">QUE_pool4007_14_1</varequal>
              </conditionvar>
              <displayfeedback feedbacktype="Response" linkrefid="QUE_pool4007_14_1_fb" />
          </respcondition>
          <respcondition continue="Yes">
              <conditionvar>
                <varequal respident="QUE_pool4007_14_RL">QUE_pool4007_14_2</varequal>
              </conditionvar>
              <displayfeedback feedbacktype="Response" linkrefid="QUE_pool4007_14_2_fb" />
          </respcondition>
          <respcondition continue="Yes">
              <conditionvar>
                <varequal respident="QUE_pool4007_14_RL">QUE_pool4007_14_3</varequal>
              </conditionvar>
              <displayfeedback feedbacktype="Response" linkrefid="QUE_pool4007_14_3_fb" />
          </respcondition>
          <respcondition continue="Yes">
              <conditionvar>
                <varequal respident="QUE_pool4007_14_RL">QUE_pool4007_14_4</varequal>
              </conditionvar>
              <displayfeedback feedbacktype="Response" linkrefid="QUE_pool4007_14_4_fb" />
          </respcondition>
          <respcondition continue="No">
            <conditionvar>
              <varequal case="Yes" respident="QUE_pool4007_14_RL">QUE_pool4007_14_3</varequal>
            </conditionvar>
            <setvar action="Set" varname="SCORE">100</setvar>
          </respcondition>
        </resprocessing>
        <itemfeedback ident="QUE_pool4007_14_1_fb">
          <material>
            <mattext texttype="text/html"></mattext>
          </material>
        </itemfeedback>
        <itemfeedback ident="QUE_pool4007_14_2_fb">
          <material>
            <mattext texttype="text/html"></mattext>
          </material>
        </itemfeedback>
        <itemfeedback ident="QUE_pool4007_14_3_fb">
          <material>
            <mattext texttype="text/html"></mattext>
          </material>
        </itemfeedback>
        <itemfeedback ident="QUE_pool4007_14_4_fb">
          <material>
            <mattext texttype="text/html"></mattext>
          </material>
        </itemfeedback>
      </item>
      <item ident="QUE_pool4007_15" title="CH-3 Network Traffic Signatures 15">
        <itemmetadata>
          <qtimetadata>
            <qtimetadatafield>
              <fieldlabel>cc_profile</fieldlabel>
              <fieldentry>cc.multiple_choice.v0p1</fieldentry>
            </qtimetadatafield>
          </qtimetadata>
        </itemmetadata>
        <presentation>
          <material>
            <mattext texttype="text/html">Which element of an ICMP header would indicate that the packet is an ICMP echo request message.</mattext>
          </material>
          <response_lid ident="QUE_pool4007_15_RL" rcardinality="Single">
            <render_choice>
              <response_label ident="QUE_pool4007_15_1">
                <material>
                  <mattext texttype="text/html">Code</mattext>
                </material>
              </response_label>
              <response_label ident="QUE_pool4007_15_2">
                <material>
                  <mattext texttype="text/html">Type</mattext>
                </material>
              </response_label>
              <response_label ident="QUE_pool4007_15_3">
                <material>
                  <mattext texttype="text/html">Identifier</mattext>
                </material>
              </response_label>
              <response_label ident="QUE_pool4007_15_4">
                <material>
                  <mattext texttype="text/html">Data</mattext>
                </material>
              </response_label>
            </render_choice>
          </response_lid>
        </presentation>
        <resprocessing>
          <outcomes>
            <decvar maxvalue="1.0" minvalue="0" varname="SCORE" vartype="Decimal"/>
          </outcomes>
          <respcondition continue="Yes">
              <conditionvar>
                <varequal respident="QUE_pool4007_15_RL">QUE_pool4007_15_1</varequal>
              </conditionvar>
              <displayfeedback feedbacktype="Response" linkrefid="QUE_pool4007_15_1_fb" />
          </respcondition>
          <respcondition continue="Yes">
              <conditionvar>
                <varequal respident="QUE_pool4007_15_RL">QUE_pool4007_15_2</varequal>
              </conditionvar>
              <displayfeedback feedbacktype="Response" linkrefid="QUE_pool4007_15_2_fb" />
          </respcondition>
          <respcondition continue="Yes">
              <conditionvar>
                <varequal respident="QUE_pool4007_15_RL">QUE_pool4007_15_3</varequal>
              </conditionvar>
              <displayfeedback feedbacktype="Response" linkrefid="QUE_pool4007_15_3_fb" />
          </respcondition>
          <respcondition continue="Yes">
              <conditionvar>
                <varequal respident="QUE_pool4007_15_RL">QUE_pool4007_15_4</varequal>
              </conditionvar>
              <displayfeedback feedbacktype="Response" linkrefid="QUE_pool4007_15_4_fb" />
          </respcondition>
          <respcondition continue="No">
            <conditionvar>
              <varequal case="Yes" respident="QUE_pool4007_15_RL">QUE_pool4007_15_2</varequal>
            </conditionvar>
            <setvar action="Set" varname="SCORE">100</setvar>
          </respcondition>
        </resprocessing>
        <itemfeedback ident="QUE_pool4007_15_1_fb">
          <material>
            <mattext texttype="text/html"></mattext>
          </material>
        </itemfeedback>
        <itemfeedback ident="QUE_pool4007_15_2_fb">
          <material>
            <mattext texttype="text/html"></mattext>
          </material>
        </itemfeedback>
        <itemfeedback ident="QUE_pool4007_15_3_fb">
          <material>
            <mattext texttype="text/html"></mattext>
          </material>
        </itemfeedback>
        <itemfeedback ident="QUE_pool4007_15_4_fb">
          <material>
            <mattext texttype="text/html"></mattext>
          </material>
        </itemfeedback>
      </item>
      <item ident="QUE_pool4007_16" title="CH-3 Network Traffic Signatures 16">
        <itemmetadata>
          <qtimetadata>
            <qtimetadatafield>
              <fieldlabel>cc_profile</fieldlabel>
              <fieldentry>cc.multiple_choice.v0p1</fieldentry>
            </qtimetadatafield>
          </qtimetadata>
        </itemmetadata>
        <presentation>
          <material>
            <mattext texttype="text/html">Which of the following is an element of the TCP header that can indicate that a connection has been established?</mattext>
          </material>
          <response_lid ident="QUE_pool4007_16_RL" rcardinality="Single">
            <render_choice>
              <response_label ident="QUE_pool4007_16_1">
                <material>
                  <mattext texttype="text/html">Flags</mattext>
                </material>
              </response_label>
              <response_label ident="QUE_pool4007_16_2">
                <material>
                  <mattext texttype="text/html">Stream index</mattext>
                </material>
              </response_label>
              <response_label ident="QUE_pool4007_16_3">
                <material>
                  <mattext texttype="text/html">SEQ/ACK analysis</mattext>
                </material>
              </response_label>
              <response_label ident="QUE_pool4007_16_4">
                <material>
                  <mattext texttype="text/html">Sequence number</mattext>
                </material>
              </response_label>
            </render_choice>
          </response_lid>
        </presentation>
        <resprocessing>
          <outcomes>
            <decvar maxvalue="1.0" minvalue="0" varname="SCORE" vartype="Decimal"/>
          </outcomes>
          <respcondition continue="Yes">
              <conditionvar>
                <varequal respident="QUE_pool4007_16_RL">QUE_pool4007_16_1</varequal>
              </conditionvar>
              <displayfeedback feedbacktype="Response" linkrefid="QUE_pool4007_16_1_fb" />
          </respcondition>
          <respcondition continue="Yes">
              <conditionvar>
                <varequal respident="QUE_pool4007_16_RL">QUE_pool4007_16_2</varequal>
              </conditionvar>
              <displayfeedback feedbacktype="Response" linkrefid="QUE_pool4007_16_2_fb" />
          </respcondition>
          <respcondition continue="Yes">
              <conditionvar>
                <varequal respident="QUE_pool4007_16_RL">QUE_pool4007_16_3</varequal>
              </conditionvar>
              <displayfeedback feedbacktype="Response" linkrefid="QUE_pool4007_16_3_fb" />
          </respcondition>
          <respcondition continue="Yes">
              <conditionvar>
                <varequal respident="QUE_pool4007_16_RL">QUE_pool4007_16_4</varequal>
              </conditionvar>
              <displayfeedback feedbacktype="Response" linkrefid="QUE_pool4007_16_4_fb" />
          </respcondition>
          <respcondition continue="No">
            <conditionvar>
              <varequal case="Yes" respident="QUE_pool4007_16_RL">QUE_pool4007_16_1</varequal>
            </conditionvar>
            <setvar action="Set" varname="SCORE">100</setvar>
          </respcondition>
        </resprocessing>
        <itemfeedback ident="QUE_pool4007_16_1_fb">
          <material>
            <mattext texttype="text/html"></mattext>
          </material>
        </itemfeedback>
        <itemfeedback ident="QUE_pool4007_16_2_fb">
          <material>
            <mattext texttype="text/html"></mattext>
          </material>
        </itemfeedback>
        <itemfeedback ident="QUE_pool4007_16_3_fb">
          <material>
            <mattext texttype="text/html"></mattext>
          </material>
        </itemfeedback>
        <itemfeedback ident="QUE_pool4007_16_4_fb">
          <material>
            <mattext texttype="text/html"></mattext>
          </material>
        </itemfeedback>
      </item>
      <item ident="QUE_pool4007_17" title="CH-3 Network Traffic Signatures 17">
        <itemmetadata>
          <qtimetadata>
            <qtimetadatafield>
              <fieldlabel>cc_profile</fieldlabel>
              <fieldentry>cc.multiple_choice.v0p1</fieldentry>
            </qtimetadatafield>
          </qtimetadata>
        </itemmetadata>
        <presentation>
          <material>
            <mattext texttype="text/html">Which TCP flag can be the default response to a probe on a closed port?</mattext>
          </material>
          <response_lid ident="QUE_pool4007_17_RL" rcardinality="Single">
            <render_choice>
              <response_label ident="QUE_pool4007_17_1">
                <material>
                  <mattext texttype="text/html">RST</mattext>
                </material>
              </response_label>
              <response_label ident="QUE_pool4007_17_2">
                <material>
                  <mattext texttype="text/html">URG</mattext>
                </material>
              </response_label>
              <response_label ident="QUE_pool4007_17_3">
                <material>
                  <mattext texttype="text/html">PSH</mattext>
                </material>
              </response_label>
              <response_label ident="QUE_pool4007_17_4">
                <material>
                  <mattext texttype="text/html">SYN</mattext>
                </material>
              </response_label>
            </render_choice>
          </response_lid>
        </presentation>
        <resprocessing>
          <outcomes>
            <decvar maxvalue="1.0" minvalue="0" varname="SCORE" vartype="Decimal"/>
          </outcomes>
          <respcondition continue="Yes">
              <conditionvar>
                <varequal respident="QUE_pool4007_17_RL">QUE_pool4007_17_1</varequal>
              </conditionvar>
              <displayfeedback feedbacktype="Response" linkrefid="QUE_pool4007_17_1_fb" />
          </respcondition>
          <respcondition continue="Yes">
              <conditionvar>
                <varequal respident="QUE_pool4007_17_RL">QUE_pool4007_17_2</varequal>
              </conditionvar>
              <displayfeedback feedbacktype="Response" linkrefid="QUE_pool4007_17_2_fb" />
          </respcondition>
          <respcondition continue="Yes">
              <conditionvar>
                <varequal respident="QUE_pool4007_17_RL">QUE_pool4007_17_3</varequal>
              </conditionvar>
              <displayfeedback feedbacktype="Response" linkrefid="QUE_pool4007_17_3_fb" />
          </respcondition>
          <respcondition continue="Yes">
              <conditionvar>
                <varequal respident="QUE_pool4007_17_RL">QUE_pool4007_17_4</varequal>
              </conditionvar>
              <displayfeedback feedbacktype="Response" linkrefid="QUE_pool4007_17_4_fb" />
          </respcondition>
          <respcondition continue="No">
            <conditionvar>
              <varequal case="Yes" respident="QUE_pool4007_17_RL">QUE_pool4007_17_1</varequal>
            </conditionvar>
            <setvar action="Set" varname="SCORE">100</setvar>
          </respcondition>
        </resprocessing>
        <itemfeedback ident="QUE_pool4007_17_1_fb">
          <material>
            <mattext texttype="text/html"></mattext>
          </material>
        </itemfeedback>
        <itemfeedback ident="QUE_pool4007_17_2_fb">
          <material>
            <mattext texttype="text/html"></mattext>
          </material>
        </itemfeedback>
        <itemfeedback ident="QUE_pool4007_17_3_fb">
          <material>
            <mattext texttype="text/html"></mattext>
          </material>
        </itemfeedback>
        <itemfeedback ident="QUE_pool4007_17_4_fb">
          <material>
            <mattext texttype="text/html"></mattext>
          </material>
        </itemfeedback>
      </item>
      <item ident="QUE_pool4007_18" title="CH-3 Network Traffic Signatures 18">
        <itemmetadata>
          <qtimetadata>
            <qtimetadatafield>
              <fieldlabel>cc_profile</fieldlabel>
              <fieldentry>cc.multiple_choice.v0p1</fieldentry>
            </qtimetadatafield>
          </qtimetadata>
        </itemmetadata>
        <presentation>
          <material>
            <mattext texttype="text/html">What is the typical packet sequence for closing a TCP session?</mattext>
          </material>
          <response_lid ident="QUE_pool4007_18_RL" rcardinality="Single">
            <render_choice>
              <response_label ident="QUE_pool4007_18_1">
                <material>
                  <mattext texttype="text/html">FIN, FIN ACK, RST</mattext>
                </material>
              </response_label>
              <response_label ident="QUE_pool4007_18_2">
                <material>
                  <mattext texttype="text/html">FIN, ACK, FIN ACK, ACK</mattext>
                </material>
              </response_label>
              <response_label ident="QUE_pool4007_18_3">
                <material>
                  <mattext texttype="text/html">FIN ACK, FIN, ACK, RST</mattext>
                </material>
              </response_label>
              <response_label ident="QUE_pool4007_18_4">
                <material>
                  <mattext texttype="text/html">FIN, FIN ACK</mattext>
                </material>
              </response_label>
            </render_choice>
          </response_lid>
        </presentation>
        <resprocessing>
          <outcomes>
            <decvar maxvalue="1.0" minvalue="0" varname="SCORE" vartype="Decimal"/>
          </outcomes>
          <respcondition continue="Yes">
              <conditionvar>
                <varequal respident="QUE_pool4007_18_RL">QUE_pool4007_18_1</varequal>
              </conditionvar>
              <displayfeedback feedbacktype="Response" linkrefid="QUE_pool4007_18_1_fb" />
          </respcondition>
          <respcondition continue="Yes">
              <conditionvar>
                <varequal respident="QUE_pool4007_18_RL">QUE_pool4007_18_2</varequal>
              </conditionvar>
              <displayfeedback feedbacktype="Response" linkrefid="QUE_pool4007_18_2_fb" />
          </respcondition>
          <respcondition continue="Yes">
              <conditionvar>
                <varequal respident="QUE_pool4007_18_RL">QUE_pool4007_18_3</varequal>
              </conditionvar>
              <displayfeedback feedbacktype="Response" linkrefid="QUE_pool4007_18_3_fb" />
          </respcondition>
          <respcondition continue="Yes">
              <conditionvar>
                <varequal respident="QUE_pool4007_18_RL">QUE_pool4007_18_4</varequal>
              </conditionvar>
              <displayfeedback feedbacktype="Response" linkrefid="QUE_pool4007_18_4_fb" />
          </respcondition>
          <respcondition continue="No">
            <conditionvar>
              <varequal case="Yes" respident="QUE_pool4007_18_RL">QUE_pool4007_18_2</varequal>
            </conditionvar>
            <setvar action="Set" varname="SCORE">100</setvar>
          </respcondition>
        </resprocessing>
        <itemfeedback ident="QUE_pool4007_18_1_fb">
          <material>
            <mattext texttype="text/html"></mattext>
          </material>
        </itemfeedback>
        <itemfeedback ident="QUE_pool4007_18_2_fb">
          <material>
            <mattext texttype="text/html"></mattext>
          </material>
        </itemfeedback>
        <itemfeedback ident="QUE_pool4007_18_3_fb">
          <material>
            <mattext texttype="text/html"></mattext>
          </material>
        </itemfeedback>
        <itemfeedback ident="QUE_pool4007_18_4_fb">
          <material>
            <mattext texttype="text/html"></mattext>
          </material>
        </itemfeedback>
      </item>
      <item ident="QUE_pool4007_19" title="CH-3 Network Traffic Signatures 19">
        <itemmetadata>
          <qtimetadata>
            <qtimetadatafield>
              <fieldlabel>cc_profile</fieldlabel>
              <fieldentry>cc.multiple_choice.v0p1</fieldentry>
            </qtimetadatafield>
          </qtimetadata>
        </itemmetadata>
        <presentation>
          <material>
            <mattext texttype="text/html">What is the sequence of packets for a successful three-way handshake?</mattext>
          </material>
          <response_lid ident="QUE_pool4007_19_RL" rcardinality="Single">
            <render_choice>
              <response_label ident="QUE_pool4007_19_1">
                <material>
                  <mattext texttype="text/html">SYN, ACK, ACK</mattext>
                </material>
              </response_label>
              <response_label ident="QUE_pool4007_19_2">
                <material>
                  <mattext texttype="text/html">SYN, SYN ACK, RST</mattext>
                </material>
              </response_label>
              <response_label ident="QUE_pool4007_19_3">
                <material>
                  <mattext texttype="text/html">SYN, SYN ACK, ACK</mattext>
                </material>
              </response_label>
              <response_label ident="QUE_pool4007_19_4">
                <material>
                  <mattext texttype="text/html">SYN, ACK, FIN</mattext>
                </material>
              </response_label>
            </render_choice>
          </response_lid>
        </presentation>
        <resprocessing>
          <outcomes>
            <decvar maxvalue="1.0" minvalue="0" varname="SCORE" vartype="Decimal"/>
          </outcomes>
          <respcondition continue="Yes">
              <conditionvar>
                <varequal respident="QUE_pool4007_19_RL">QUE_pool4007_19_1</varequal>
              </conditionvar>
              <displayfeedback feedbacktype="Response" linkrefid="QUE_pool4007_19_1_fb" />
          </respcondition>
          <respcondition continue="Yes">
              <conditionvar>
                <varequal respident="QUE_pool4007_19_RL">QUE_pool4007_19_2</varequal>
              </conditionvar>
              <displayfeedback feedbacktype="Response" linkrefid="QUE_pool4007_19_2_fb" />
          </respcondition>
          <respcondition continue="Yes">
              <conditionvar>
                <varequal respident="QUE_pool4007_19_RL">QUE_pool4007_19_3</varequal>
              </conditionvar>
              <displayfeedback feedbacktype="Response" linkrefid="QUE_pool4007_19_3_fb" />
          </respcondition>
          <respcondition continue="Yes">
              <conditionvar>
                <varequal respident="QUE_pool4007_19_RL">QUE_pool4007_19_4</varequal>
              </conditionvar>
              <displayfeedback feedbacktype="Response" linkrefid="QUE_pool4007_19_4_fb" />
          </respcondition>
          <respcondition continue="No">
            <conditionvar>
              <varequal case="Yes" respident="QUE_pool4007_19_RL">QUE_pool4007_19_3</varequal>
            </conditionvar>
            <setvar action="Set" varname="SCORE">100</setvar>
          </respcondition>
        </resprocessing>
        <itemfeedback ident="QUE_pool4007_19_1_fb">
          <material>
            <mattext texttype="text/html"></mattext>
          </material>
        </itemfeedback>
        <itemfeedback ident="QUE_pool4007_19_2_fb">
          <material>
            <mattext texttype="text/html"></mattext>
          </material>
        </itemfeedback>
        <itemfeedback ident="QUE_pool4007_19_3_fb">
          <material>
            <mattext texttype="text/html"></mattext>
          </material>
        </itemfeedback>
        <itemfeedback ident="QUE_pool4007_19_4_fb">
          <material>
            <mattext texttype="text/html"></mattext>
          </material>
        </itemfeedback>
      </item>
      <item ident="QUE_pool4007_20" title="CH-3 Network Traffic Signatures 20">
        <itemmetadata>
          <qtimetadata>
            <qtimetadatafield>
              <fieldlabel>cc_profile</fieldlabel>
              <fieldentry>cc.multiple_choice.v0p1</fieldentry>
            </qtimetadatafield>
          </qtimetadata>
        </itemmetadata>
        <presentation>
          <material>
            <mattext texttype="text/html">Which of the following correctly represents the port used by FTP control traffic and FTP file transfer traffic respectively?</mattext>
          </material>
          <response_lid ident="QUE_pool4007_20_RL" rcardinality="Single">
            <render_choice>
              <response_label ident="QUE_pool4007_20_1">
                <material>
                  <mattext texttype="text/html">20, 25</mattext>
                </material>
              </response_label>
              <response_label ident="QUE_pool4007_20_2">
                <material>
                  <mattext texttype="text/html">21, 23</mattext>
                </material>
              </response_label>
              <response_label ident="QUE_pool4007_20_3">
                <material>
                  <mattext texttype="text/html">20, 23</mattext>
                </material>
              </response_label>
              <response_label ident="QUE_pool4007_20_4">
                <material>
                  <mattext texttype="text/html">21, 20</mattext>
                </material>
              </response_label>
            </render_choice>
          </response_lid>
        </presentation>
        <resprocessing>
          <outcomes>
            <decvar maxvalue="1.0" minvalue="0" varname="SCORE" vartype="Decimal"/>
          </outcomes>
          <respcondition continue="Yes">
              <conditionvar>
                <varequal respident="QUE_pool4007_20_RL">QUE_pool4007_20_1</varequal>
              </conditionvar>
              <displayfeedback feedbacktype="Response" linkrefid="QUE_pool4007_20_1_fb" />
          </respcondition>
          <respcondition continue="Yes">
              <conditionvar>
                <varequal respident="QUE_pool4007_20_RL">QUE_pool4007_20_2</varequal>
              </conditionvar>
              <displayfeedback feedbacktype="Response" linkrefid="QUE_pool4007_20_2_fb" />
          </respcondition>
          <respcondition continue="Yes">
              <conditionvar>
                <varequal respident="QUE_pool4007_20_RL">QUE_pool4007_20_3</varequal>
              </conditionvar>
              <displayfeedback feedbacktype="Response" linkrefid="QUE_pool4007_20_3_fb" />
          </respcondition>
          <respcondition continue="Yes">
              <conditionvar>
                <varequal respident="QUE_pool4007_20_RL">QUE_pool4007_20_4</varequal>
              </conditionvar>
              <displayfeedback feedbacktype="Response" linkrefid="QUE_pool4007_20_4_fb" />
          </respcondition>
          <respcondition continue="No">
            <conditionvar>
              <varequal case="Yes" respident="QUE_pool4007_20_RL">QUE_pool4007_20_4</varequal>
            </conditionvar>
            <setvar action="Set" varname="SCORE">100</setvar>
          </respcondition>
        </resprocessing>
        <itemfeedback ident="QUE_pool4007_20_1_fb">
          <material>
            <mattext texttype="text/html"></mattext>
          </material>
        </itemfeedback>
        <itemfeedback ident="QUE_pool4007_20_2_fb">
          <material>
            <mattext texttype="text/html"></mattext>
          </material>
        </itemfeedback>
        <itemfeedback ident="QUE_pool4007_20_3_fb">
          <material>
            <mattext texttype="text/html"></mattext>
          </material>
        </itemfeedback>
        <itemfeedback ident="QUE_pool4007_20_4_fb">
          <material>
            <mattext texttype="text/html"></mattext>
          </material>
        </itemfeedback>
      </item>
      <item ident="QUE_pool4007_21" title="CH-3 Network Traffic Signatures 21">
        <itemmetadata>
          <qtimetadata>
            <qtimetadatafield>
              <fieldlabel>cc_profile</fieldlabel>
              <fieldentry>cc.multiple_choice.v0p1</fieldentry>
            </qtimetadatafield>
          </qtimetadata>
        </itemmetadata>
        <presentation>
          <material>
            <mattext texttype="text/html">What is the packet called where a Web browser sends a request to the Web server for Web page data?</mattext>
          </material>
          <response_lid ident="QUE_pool4007_21_RL" rcardinality="Single">
            <render_choice>
              <response_label ident="QUE_pool4007_21_1">
                <material>
                  <mattext texttype="text/html">HTML SEND</mattext>
                </material>
              </response_label>
              <response_label ident="QUE_pool4007_21_2">
                <material>
                  <mattext texttype="text/html">HTTP XFER</mattext>
                </material>
              </response_label>
              <response_label ident="QUE_pool4007_21_3">
                <material>
                  <mattext texttype="text/html">HTTP GET</mattext>
                </material>
              </response_label>
              <response_label ident="QUE_pool4007_21_4">
                <material>
                  <mattext texttype="text/html">HTML RELAY</mattext>
                </material>
              </response_label>
            </render_choice>
          </response_lid>
        </presentation>
        <resprocessing>
          <outcomes>
            <decvar maxvalue="1.0" minvalue="0" varname="SCORE" vartype="Decimal"/>
          </outcomes>
          <respcondition continue="Yes">
              <conditionvar>
                <varequal respident="QUE_pool4007_21_RL">QUE_pool4007_21_1</varequal>
              </conditionvar>
              <displayfeedback feedbacktype="Response" linkrefid="QUE_pool4007_21_1_fb" />
          </respcondition>
          <respcondition continue="Yes">
              <conditionvar>
                <varequal respident="QUE_pool4007_21_RL">QUE_pool4007_21_2</varequal>
              </conditionvar>
              <displayfeedback feedbacktype="Response" linkrefid="QUE_pool4007_21_2_fb" />
          </respcondition>
          <respcondition continue="Yes">
              <conditionvar>
                <varequal respident="QUE_pool4007_21_RL">QUE_pool4007_21_3</varequal>
              </conditionvar>
              <displayfeedback feedbacktype="Response" linkrefid="QUE_pool4007_21_3_fb" />
          </respcondition>
          <respcondition continue="Yes">
              <conditionvar>
                <varequal respident="QUE_pool4007_21_RL">QUE_pool4007_21_4</varequal>
              </conditionvar>
              <displayfeedback feedbacktype="Response" linkrefid="QUE_pool4007_21_4_fb" />
          </respcondition>
          <respcondition continue="No">
            <conditionvar>
              <varequal case="Yes" respident="QUE_pool4007_21_RL">QUE_pool4007_21_3</varequal>
            </conditionvar>
            <setvar action="Set" varname="SCORE">100</setvar>
          </respcondition>
        </resprocessing>
        <itemfeedback ident="QUE_pool4007_21_1_fb">
          <material>
            <mattext texttype="text/html"></mattext>
          </material>
        </itemfeedback>
        <itemfeedback ident="QUE_pool4007_21_2_fb">
          <material>
            <mattext texttype="text/html"></mattext>
          </material>
        </itemfeedback>
        <itemfeedback ident="QUE_pool4007_21_3_fb">
          <material>
            <mattext texttype="text/html"></mattext>
          </material>
        </itemfeedback>
        <itemfeedback ident="QUE_pool4007_21_4_fb">
          <material>
            <mattext texttype="text/html"></mattext>
          </material>
        </itemfeedback>
      </item>
      <item ident="QUE_pool4007_22" title="CH-3 Network Traffic Signatures 22">
        <itemmetadata>
          <qtimetadata>
            <qtimetadatafield>
              <fieldlabel>cc_profile</fieldlabel>
              <fieldentry>cc.multiple_choice.v0p1</fieldentry>
            </qtimetadatafield>
          </qtimetadata>
        </itemmetadata>
        <presentation>
          <material>
            <mattext texttype="text/html">Under which suspicious traffic signature category would a port scan fall?</mattext>
          </material>
          <response_lid ident="QUE_pool4007_22_RL" rcardinality="Single">
            <render_choice>
              <response_label ident="QUE_pool4007_22_1">
                <material>
                  <mattext texttype="text/html">informational</mattext>
                </material>
              </response_label>
              <response_label ident="QUE_pool4007_22_2">
                <material>
                  <mattext texttype="text/html">reconnaissance</mattext>
                </material>
              </response_label>
              <response_label ident="QUE_pool4007_22_3">
                <material>
                  <mattext texttype="text/html">denial of service</mattext>
                </material>
              </response_label>
              <response_label ident="QUE_pool4007_22_4">
                <material>
                  <mattext texttype="text/html">unauthorized access</mattext>
                </material>
              </response_label>
            </render_choice>
          </response_lid>
        </presentation>
        <resprocessing>
          <outcomes>
            <decvar maxvalue="1.0" minvalue="0" varname="SCORE" vartype="Decimal"/>
          </outcomes>
          <respcondition continue="Yes">
              <conditionvar>
                <varequal respident="QUE_pool4007_22_RL">QUE_pool4007_22_1</varequal>
              </conditionvar>
              <displayfeedback feedbacktype="Response" linkrefid="QUE_pool4007_22_1_fb" />
          </respcondition>
          <respcondition continue="Yes">
              <conditionvar>
                <varequal respident="QUE_pool4007_22_RL">QUE_pool4007_22_2</varequal>
              </conditionvar>
              <displayfeedback feedbacktype="Response" linkrefid="QUE_pool4007_22_2_fb" />
          </respcondition>
          <respcondition continue="Yes">
              <conditionvar>
                <varequal respident="QUE_pool4007_22_RL">QUE_pool4007_22_3</varequal>
              </conditionvar>
              <displayfeedback feedbacktype="Response" linkrefid="QUE_pool4007_22_3_fb" />
          </respcondition>
          <respcondition continue="Yes">
              <conditionvar>
                <varequal respident="QUE_pool4007_22_RL">QUE_pool4007_22_4</varequal>
              </conditionvar>
              <displayfeedback feedbacktype="Response" linkrefid="QUE_pool4007_22_4_fb" />
          </respcondition>
          <respcondition continue="No">
            <conditionvar>
              <varequal case="Yes" respident="QUE_pool4007_22_RL">QUE_pool4007_22_2</varequal>
            </conditionvar>
            <setvar action="Set" varname="SCORE">100</setvar>
          </respcondition>
        </resprocessing>
        <itemfeedback ident="QUE_pool4007_22_1_fb">
          <material>
            <mattext texttype="text/html"></mattext>
          </material>
        </itemfeedback>
        <itemfeedback ident="QUE_pool4007_22_2_fb">
          <material>
            <mattext texttype="text/html"></mattext>
          </material>
        </itemfeedback>
        <itemfeedback ident="QUE_pool4007_22_3_fb">
          <material>
            <mattext texttype="text/html"></mattext>
          </material>
        </itemfeedback>
        <itemfeedback ident="QUE_pool4007_22_4_fb">
          <material>
            <mattext texttype="text/html"></mattext>
          </material>
        </itemfeedback>
      </item>
      <item ident="QUE_pool4007_23" title="CH-3 Network Traffic Signatures 23">
        <itemmetadata>
          <qtimetadata>
            <qtimetadatafield>
              <fieldlabel>cc_profile</fieldlabel>
              <fieldentry>cc.multiple_choice.v0p1</fieldentry>
            </qtimetadatafield>
          </qtimetadata>
        </itemmetadata>
        <presentation>
          <material>
            <mattext texttype="text/html">In which type of scan does an attacker scan only ports that are commonly used by specific programs?</mattext>
          </material>
          <response_lid ident="QUE_pool4007_23_RL" rcardinality="Single">
            <render_choice>
              <response_label ident="QUE_pool4007_23_1">
                <material>
                  <mattext texttype="text/html">random scan</mattext>
                </material>
              </response_label>
              <response_label ident="QUE_pool4007_23_2">
                <material>
                  <mattext texttype="text/html">vanilla scan</mattext>
                </material>
              </response_label>
              <response_label ident="QUE_pool4007_23_3">
                <material>
                  <mattext texttype="text/html">ping sweep</mattext>
                </material>
              </response_label>
              <response_label ident="QUE_pool4007_23_4">
                <material>
                  <mattext texttype="text/html">strobe scan</mattext>
                </material>
              </response_label>
            </render_choice>
          </response_lid>
        </presentation>
        <resprocessing>
          <outcomes>
            <decvar maxvalue="1.0" minvalue="0" varname="SCORE" vartype="Decimal"/>
          </outcomes>
          <respcondition continue="Yes">
              <conditionvar>
                <varequal respident="QUE_pool4007_23_RL">QUE_pool4007_23_1</varequal>
              </conditionvar>
              <displayfeedback feedbacktype="Response" linkrefid="QUE_pool4007_23_1_fb" />
          </respcondition>
          <respcondition continue="Yes">
              <conditionvar>
                <varequal respident="QUE_pool4007_23_RL">QUE_pool4007_23_2</varequal>
              </conditionvar>
              <displayfeedback feedbacktype="Response" linkrefid="QUE_pool4007_23_2_fb" />
          </respcondition>
          <respcondition continue="Yes">
              <conditionvar>
                <varequal respident="QUE_pool4007_23_RL">QUE_pool4007_23_3</varequal>
              </conditionvar>
              <displayfeedback feedbacktype="Response" linkrefid="QUE_pool4007_23_3_fb" />
          </respcondition>
          <respcondition continue="Yes">
              <conditionvar>
                <varequal respident="QUE_pool4007_23_RL">QUE_pool4007_23_4</varequal>
              </conditionvar>
              <displayfeedback feedbacktype="Response" linkrefid="QUE_pool4007_23_4_fb" />
          </respcondition>
          <respcondition continue="No">
            <conditionvar>
              <varequal case="Yes" respident="QUE_pool4007_23_RL">QUE_pool4007_23_4</varequal>
            </conditionvar>
            <setvar action="Set" varname="SCORE">100</setvar>
          </respcondition>
        </resprocessing>
        <itemfeedback ident="QUE_pool4007_23_1_fb">
          <material>
            <mattext texttype="text/html"></mattext>
          </material>
        </itemfeedback>
        <itemfeedback ident="QUE_pool4007_23_2_fb">
          <material>
            <mattext texttype="text/html"></mattext>
          </material>
        </itemfeedback>
        <itemfeedback ident="QUE_pool4007_23_3_fb">
          <material>
            <mattext texttype="text/html"></mattext>
          </material>
        </itemfeedback>
        <itemfeedback ident="QUE_pool4007_23_4_fb">
          <material>
            <mattext texttype="text/html"></mattext>
          </material>
        </itemfeedback>
      </item>
      <item ident="QUE_pool4007_24" title="CH-3 Network Traffic Signatures 24">
        <itemmetadata>
          <qtimetadata>
            <qtimetadatafield>
              <fieldlabel>cc_profile</fieldlabel>
              <fieldentry>cc.multiple_choice.v0p1</fieldentry>
            </qtimetadatafield>
          </qtimetadata>
        </itemmetadata>
        <presentation>
          <material>
            <mattext texttype="text/html">Which type of scan has the FIN, PSH, and URG flags set?</mattext>
          </material>
          <response_lid ident="QUE_pool4007_24_RL" rcardinality="Single">
            <render_choice>
              <response_label ident="QUE_pool4007_24_1">
                <material>
                  <mattext texttype="text/html">Xmas scan</mattext>
                </material>
              </response_label>
              <response_label ident="QUE_pool4007_24_2">
                <material>
                  <mattext texttype="text/html">Null scan</mattext>
                </material>
              </response_label>
              <response_label ident="QUE_pool4007_24_3">
                <material>
                  <mattext texttype="text/html">FIN scan</mattext>
                </material>
              </response_label>
              <response_label ident="QUE_pool4007_24_4">
                <material>
                  <mattext texttype="text/html">SYN Scan</mattext>
                </material>
              </response_label>
            </render_choice>
          </response_lid>
        </presentation>
        <resprocessing>
          <outcomes>
            <decvar maxvalue="1.0" minvalue="0" varname="SCORE" vartype="Decimal"/>
          </outcomes>
          <respcondition continue="Yes">
              <conditionvar>
                <varequal respident="QUE_pool4007_24_RL">QUE_pool4007_24_1</varequal>
              </conditionvar>
              <displayfeedback feedbacktype="Response" linkrefid="QUE_pool4007_24_1_fb" />
          </respcondition>
          <respcondition continue="Yes">
              <conditionvar>
                <varequal respident="QUE_pool4007_24_RL">QUE_pool4007_24_2</varequal>
              </conditionvar>
              <displayfeedback feedbacktype="Response" linkrefid="QUE_pool4007_24_2_fb" />
          </respcondition>
          <respcondition continue="Yes">
              <conditionvar>
                <varequal respident="QUE_pool4007_24_RL">QUE_pool4007_24_3</varequal>
              </conditionvar>
              <displayfeedback feedbacktype="Response" linkrefid="QUE_pool4007_24_3_fb" />
          </respcondition>
          <respcondition continue="Yes">
              <conditionvar>
                <varequal respident="QUE_pool4007_24_RL">QUE_pool4007_24_4</varequal>
              </conditionvar>
              <displayfeedback feedbacktype="Response" linkrefid="QUE_pool4007_24_4_fb" />
          </respcondition>
          <respcondition continue="No">
            <conditionvar>
              <varequal case="Yes" respident="QUE_pool4007_24_RL">QUE_pool4007_24_1</varequal>
            </conditionvar>
            <setvar action="Set" varname="SCORE">100</setvar>
          </respcondition>
        </resprocessing>
        <itemfeedback ident="QUE_pool4007_24_1_fb">
          <material>
            <mattext texttype="text/html"></mattext>
          </material>
        </itemfeedback>
        <itemfeedback ident="QUE_pool4007_24_2_fb">
          <material>
            <mattext texttype="text/html"></mattext>
          </material>
        </itemfeedback>
        <itemfeedback ident="QUE_pool4007_24_3_fb">
          <material>
            <mattext texttype="text/html"></mattext>
          </material>
        </itemfeedback>
        <itemfeedback ident="QUE_pool4007_24_4_fb">
          <material>
            <mattext texttype="text/html"></mattext>
          </material>
        </itemfeedback>
      </item>
      <item ident="QUE_pool4007_25" title="CH-3 Network Traffic Signatures 25">
        <itemmetadata>
          <qtimetadata>
            <qtimetadatafield>
              <fieldlabel>cc_profile</fieldlabel>
              <fieldentry>cc.multiple_choice.v0p1</fieldentry>
            </qtimetadatafield>
          </qtimetadata>
        </itemmetadata>
        <presentation>
          <material>
            <mattext texttype="text/html">Which of the following is the description of a land attack?</mattext>
          </material>
          <response_lid ident="QUE_pool4007_25_RL" rcardinality="Single">
            <render_choice>
              <response_label ident="QUE_pool4007_25_1">
                <material>
                  <mattext texttype="text/html">the local host source address occurs in the packet</mattext>
                </material>
              </response_label>
              <response_label ident="QUE_pool4007_25_2">
                <material>
                  <mattext texttype="text/html">source and destination IP address/port are the same</mattext>
                </material>
              </response_label>
              <response_label ident="QUE_pool4007_25_3">
                <material>
                  <mattext texttype="text/html">an illegal TCP flag is found in the segment header</mattext>
                </material>
              </response_label>
              <response_label ident="QUE_pool4007_25_4">
                <material>
                  <mattext texttype="text/html">the attacker uses an undefined protocol number</mattext>
                </material>
              </response_label>
            </render_choice>
          </response_lid>
        </presentation>
        <resprocessing>
          <outcomes>
            <decvar maxvalue="1.0" minvalue="0" varname="SCORE" vartype="Decimal"/>
          </outcomes>
          <respcondition continue="Yes">
              <conditionvar>
                <varequal respident="QUE_pool4007_25_RL">QUE_pool4007_25_1</varequal>
              </conditionvar>
              <displayfeedback feedbacktype="Response" linkrefid="QUE_pool4007_25_1_fb" />
          </respcondition>
          <respcondition continue="Yes">
              <conditionvar>
                <varequal respident="QUE_pool4007_25_RL">QUE_pool4007_25_2</varequal>
              </conditionvar>
              <displayfeedback feedbacktype="Response" linkrefid="QUE_pool4007_25_2_fb" />
          </respcondition>
          <respcondition continue="Yes">
              <conditionvar>
                <varequal respident="QUE_pool4007_25_RL">QUE_pool4007_25_3</varequal>
              </conditionvar>
              <displayfeedback feedbacktype="Response" linkrefid="QUE_pool4007_25_3_fb" />
          </respcondition>
          <respcondition continue="Yes">
              <conditionvar>
                <varequal respident="QUE_pool4007_25_RL">QUE_pool4007_25_4</varequal>
              </conditionvar>
              <displayfeedback feedbacktype="Response" linkrefid="QUE_pool4007_25_4_fb" />
          </respcondition>
          <respcondition continue="No">
            <conditionvar>
              <varequal case="Yes" respident="QUE_pool4007_25_RL">QUE_pool4007_25_2</varequal>
            </conditionvar>
            <setvar action="Set" varname="SCORE">100</setvar>
          </respcondition>
        </resprocessing>
        <itemfeedback ident="QUE_pool4007_25_1_fb">
          <material>
            <mattext texttype="text/html"></mattext>
          </material>
        </itemfeedback>
        <itemfeedback ident="QUE_pool4007_25_2_fb">
          <material>
            <mattext texttype="text/html"></mattext>
          </material>
        </itemfeedback>
        <itemfeedback ident="QUE_pool4007_25_3_fb">
          <material>
            <mattext texttype="text/html"></mattext>
          </material>
        </itemfeedback>
        <itemfeedback ident="QUE_pool4007_25_4_fb">
          <material>
            <mattext texttype="text/html"></mattext>
          </material>
        </itemfeedback>
      </item>
      <item ident="QUE_pool4007_26" title="CH-3 Network Traffic Signatures 26">
        <itemmetadata>
          <qtimetadata>
            <qtimetadatafield>
              <fieldlabel>cc_profile</fieldlabel>
              <fieldentry>cc.fib.v0p1</fieldentry>
            </qtimetadatafield>
          </qtimetadata>
        </itemmetadata>
        <presentation>
          <material>
            <mattext texttype="text/html">A ______________ is made up of IP numbers and options, TCP flags, and port number that define a type of network activity. </mattext>
          </material>
          <response_str ident="QUE_pool4007_26_RL">
            <render_fib columns="30" rows="1"/>
          </response_str>
        </presentation>
        <resprocessing>
          <outcomes>
            <decvar maxvalue="1.0" minvalue="0" varname="SCORE" vartype="Decimal"/>
          </outcomes>
          <respcondition continue="No">
            <conditionvar>
              <varequal case="No" respident="QUE_pool4007_26_RL">signature</varequal>
            </conditionvar>
            <setvar action="Set" varname="SCORE">100</setvar>
          </respcondition>
        </resprocessing>
      </item>
      <item ident="QUE_pool4007_27" title="CH-3 Network Traffic Signatures 27">
        <itemmetadata>
          <qtimetadata>
            <qtimetadatafield>
              <fieldlabel>cc_profile</fieldlabel>
              <fieldentry>cc.fib.v0p1</fieldentry>
            </qtimetadatafield>
          </qtimetadata>
        </itemmetadata>
        <presentation>
          <material>
            <mattext texttype="text/html">The _______________ part of a packet is the actual data sent from an application on one computer to an application on another. </mattext>
          </material>
          <response_str ident="QUE_pool4007_27_RL">
            <render_fib columns="30" rows="1"/>
          </response_str>
        </presentation>
        <resprocessing>
          <outcomes>
            <decvar maxvalue="1.0" minvalue="0" varname="SCORE" vartype="Decimal"/>
          </outcomes>
          <respcondition continue="No">
            <conditionvar>
              <varequal case="No" respident="QUE_pool4007_27_RL">payload</varequal>
            </conditionvar>
            <setvar action="Set" varname="SCORE">100</setvar>
          </respcondition>
        </resprocessing>
      </item>
      <item ident="QUE_pool4007_28" title="CH-3 Network Traffic Signatures 28">
        <itemmetadata>
          <qtimetadata>
            <qtimetadatafield>
              <fieldlabel>cc_profile</fieldlabel>
              <fieldentry>cc.fib.v0p1</fieldentry>
            </qtimetadatafield>
          </qtimetadata>
        </itemmetadata>
        <presentation>
          <material>
            <mattext texttype="text/html">In the three-way handshake, the first packet in the sequence has the ________ flag set. </mattext>
          </material>
          <response_str ident="QUE_pool4007_28_RL">
            <render_fib columns="30" rows="1"/>
          </response_str>
        </presentation>
        <resprocessing>
          <outcomes>
            <decvar maxvalue="1.0" minvalue="0" varname="SCORE" vartype="Decimal"/>
          </outcomes>
          <respcondition continue="No">
            <conditionvar>
              <varequal case="No" respident="QUE_pool4007_28_RL">SYN</varequal>
            </conditionvar>
            <setvar action="Set" varname="SCORE">100</setvar>
          </respcondition>
        </resprocessing>
      </item>
      <item ident="QUE_pool4007_29" title="CH-3 Network Traffic Signatures 29">
        <itemmetadata>
          <qtimetadata>
            <qtimetadatafield>
              <fieldlabel>cc_profile</fieldlabel>
              <fieldentry>cc.fib.v0p1</fieldentry>
            </qtimetadatafield>
          </qtimetadata>
        </itemmetadata>
        <presentation>
          <material>
            <mattext texttype="text/html">A TCP packet with no flags set is referred to as a _________ packet. </mattext>
          </material>
          <response_str ident="QUE_pool4007_29_RL">
            <render_fib columns="30" rows="1"/>
          </response_str>
        </presentation>
        <resprocessing>
          <outcomes>
            <decvar maxvalue="1.0" minvalue="0" varname="SCORE" vartype="Decimal"/>
          </outcomes>
          <respcondition continue="No">
            <conditionvar>
              <varequal case="No" respident="QUE_pool4007_29_RL">null</varequal>
            </conditionvar>
            <setvar action="Set" varname="SCORE">100</setvar>
          </respcondition>
        </resprocessing>
      </item>
      <item ident="QUE_pool4007_30" title="CH-3 Network Traffic Signatures 30">
        <itemmetadata>
          <qtimetadata>
            <qtimetadatafield>
              <fieldlabel>cc_profile</fieldlabel>
              <fieldentry>cc.fib.v0p1</fieldentry>
            </qtimetadatafield>
          </qtimetadata>
        </itemmetadata>
        <presentation>
          <material>
            <mattext texttype="text/html">In an RPC _________, a targeted host receives an RPC set request from a source IP address of 127.0.0.1. </mattext>
          </material>
          <response_str ident="QUE_pool4007_30_RL">
            <render_fib columns="30" rows="1"/>
          </response_str>
        </presentation>
        <resprocessing>
          <outcomes>
            <decvar maxvalue="1.0" minvalue="0" varname="SCORE" vartype="Decimal"/>
          </outcomes>
          <respcondition continue="No">
            <conditionvar>
              <varequal case="No" respident="QUE_pool4007_30_RL">set spoof</varequal>
            </conditionvar>
            <setvar action="Set" varname="SCORE">100</setvar>
          </respcondition>
        </resprocessing>
      </item>
  </objectbank>
</questestinterop>
