<?xml version="1.0" encoding="UTF-8"?>
<questestinterop xmlns="http://www.imsglobal.org/xsd/ims_qtiasiv1p2"
xmlns:xsi="http://www.w3.org/2001/XMLSchema-instance" xsi:schemaLocation="http://www.imsglobal.org/xsd/ims_qtiasiv1p2 http://www.imsglobal.org/profile/cc/ccv1p3/ccv1p3_qtiasiv1p2p1_v1p0.xsd">
  <objectbank ident="QDB_1">
      <item ident="QUE_pool13685_1" title="MCQ16 1">
        <itemmetadata>
          <qtimetadata>
            <qtimetadatafield>
              <fieldlabel>cc_profile</fieldlabel>
              <fieldentry>cc.multiple_choice.v0p1</fieldentry>
            </qtimetadatafield>
          </qtimetadata>
        </itemmetadata>
        <presentation>
          <material>
            <mattext texttype="text/html">NS3, which class is responsible for configuring and managing the physical layer in a 3G simulation?</mattext>
          </material>
          <response_lid ident="QUE_pool13685_1_RL" rcardinality="Single">
            <render_choice>
              <response_label ident="QUE_pool13685_1_1">
                <material>
                  <mattext texttype="text/html">LteSpectrumPhy class</mattext>
                </material>
              </response_label>
              <response_label ident="QUE_pool13685_1_2">
                <material>
                  <mattext texttype="text/html">UmtsPhy class</mattext>
                </material>
              </response_label>
              <response_label ident="QUE_pool13685_1_3">
                <material>
                  <mattext texttype="text/html">SpectrumHelper class</mattext>
                </material>
              </response_label>
              <response_label ident="QUE_pool13685_1_4">
                <material>
                  <mattext texttype="text/html">LteHelper class</mattext>
                </material>
              </response_label>
            </render_choice>
          </response_lid>
        </presentation>
        <resprocessing>
          <outcomes>
            <decvar maxvalue="1.0" minvalue="0" varname="SCORE" vartype="Decimal"/>
          </outcomes>
          <respcondition continue="Yes">
              <conditionvar>
                <varequal respident="QUE_pool13685_1_RL">QUE_pool13685_1_1</varequal>
              </conditionvar>
              <displayfeedback feedbacktype="Response" linkrefid="QUE_pool13685_1_1_fb" />
          </respcondition>
          <respcondition continue="Yes">
              <conditionvar>
                <varequal respident="QUE_pool13685_1_RL">QUE_pool13685_1_2</varequal>
              </conditionvar>
              <displayfeedback feedbacktype="Response" linkrefid="QUE_pool13685_1_2_fb" />
          </respcondition>
          <respcondition continue="Yes">
              <conditionvar>
                <varequal respident="QUE_pool13685_1_RL">QUE_pool13685_1_3</varequal>
              </conditionvar>
              <displayfeedback feedbacktype="Response" linkrefid="QUE_pool13685_1_3_fb" />
          </respcondition>
          <respcondition continue="Yes">
              <conditionvar>
                <varequal respident="QUE_pool13685_1_RL">QUE_pool13685_1_4</varequal>
              </conditionvar>
              <displayfeedback feedbacktype="Response" linkrefid="QUE_pool13685_1_4_fb" />
          </respcondition>
          <respcondition continue="No">
            <conditionvar>
              <varequal case="Yes" respident="QUE_pool13685_1_RL">QUE_pool13685_1_2</varequal>
            </conditionvar>
            <setvar action="Set" varname="SCORE">100</setvar>
          </respcondition>
        </resprocessing>
        <itemfeedback ident="QUE_pool13685_1_1_fb">
          <material>
            <mattext texttype="text/html"></mattext>
          </material>
        </itemfeedback>
        <itemfeedback ident="QUE_pool13685_1_2_fb">
          <material>
            <mattext texttype="text/html"></mattext>
          </material>
        </itemfeedback>
        <itemfeedback ident="QUE_pool13685_1_3_fb">
          <material>
            <mattext texttype="text/html"></mattext>
          </material>
        </itemfeedback>
        <itemfeedback ident="QUE_pool13685_1_4_fb">
          <material>
            <mattext texttype="text/html"></mattext>
          </material>
        </itemfeedback>
      </item>
      <item ident="QUE_pool13685_2" title="MCQ16 2">
        <itemmetadata>
          <qtimetadata>
            <qtimetadatafield>
              <fieldlabel>cc_profile</fieldlabel>
              <fieldentry>cc.multiple_choice.v0p1</fieldentry>
            </qtimetadatafield>
          </qtimetadata>
        </itemmetadata>
        <presentation>
          <material>
            <mattext texttype="text/html">Which parameter in NS3 controls the transmission power of a mobile device in a 3G simulation?</mattext>
          </material>
          <response_lid ident="QUE_pool13685_2_RL" rcardinality="Single">
            <render_choice>
              <response_label ident="QUE_pool13685_2_1">
                <material>
                  <mattext texttype="text/html">TxPower</mattext>
                </material>
              </response_label>
              <response_label ident="QUE_pool13685_2_2">
                <material>
                  <mattext texttype="text/html">PowerLevel</mattext>
                </material>
              </response_label>
              <response_label ident="QUE_pool13685_2_3">
                <material>
                  <mattext texttype="text/html">Gain</mattext>
                </material>
              </response_label>
              <response_label ident="QUE_pool13685_2_4">
                <material>
                  <mattext texttype="text/html">SignalStrength</mattext>
                </material>
              </response_label>
            </render_choice>
          </response_lid>
        </presentation>
        <resprocessing>
          <outcomes>
            <decvar maxvalue="1.0" minvalue="0" varname="SCORE" vartype="Decimal"/>
          </outcomes>
          <respcondition continue="Yes">
              <conditionvar>
                <varequal respident="QUE_pool13685_2_RL">QUE_pool13685_2_1</varequal>
              </conditionvar>
              <displayfeedback feedbacktype="Response" linkrefid="QUE_pool13685_2_1_fb" />
          </respcondition>
          <respcondition continue="Yes">
              <conditionvar>
                <varequal respident="QUE_pool13685_2_RL">QUE_pool13685_2_2</varequal>
              </conditionvar>
              <displayfeedback feedbacktype="Response" linkrefid="QUE_pool13685_2_2_fb" />
          </respcondition>
          <respcondition continue="Yes">
              <conditionvar>
                <varequal respident="QUE_pool13685_2_RL">QUE_pool13685_2_3</varequal>
              </conditionvar>
              <displayfeedback feedbacktype="Response" linkrefid="QUE_pool13685_2_3_fb" />
          </respcondition>
          <respcondition continue="Yes">
              <conditionvar>
                <varequal respident="QUE_pool13685_2_RL">QUE_pool13685_2_4</varequal>
              </conditionvar>
              <displayfeedback feedbacktype="Response" linkrefid="QUE_pool13685_2_4_fb" />
          </respcondition>
          <respcondition continue="No">
            <conditionvar>
              <varequal case="Yes" respident="QUE_pool13685_2_RL">QUE_pool13685_2_1</varequal>
            </conditionvar>
            <setvar action="Set" varname="SCORE">100</setvar>
          </respcondition>
        </resprocessing>
        <itemfeedback ident="QUE_pool13685_2_1_fb">
          <material>
            <mattext texttype="text/html"></mattext>
          </material>
        </itemfeedback>
        <itemfeedback ident="QUE_pool13685_2_2_fb">
          <material>
            <mattext texttype="text/html"></mattext>
          </material>
        </itemfeedback>
        <itemfeedback ident="QUE_pool13685_2_3_fb">
          <material>
            <mattext texttype="text/html"></mattext>
          </material>
        </itemfeedback>
        <itemfeedback ident="QUE_pool13685_2_4_fb">
          <material>
            <mattext texttype="text/html"></mattext>
          </material>
        </itemfeedback>
      </item>
      <item ident="QUE_pool13685_3" title="MCQ16 3">
        <itemmetadata>
          <qtimetadata>
            <qtimetadatafield>
              <fieldlabel>cc_profile</fieldlabel>
              <fieldentry>cc.multiple_choice.v0p1</fieldentry>
            </qtimetadatafield>
          </qtimetadata>
        </itemmetadata>
        <presentation>
          <material>
            <mattext texttype="text/html">In NS3, which class is responsible for generating and managing packet traffic in a 3G simulation?</mattext>
          </material>
          <response_lid ident="QUE_pool13685_3_RL" rcardinality="Single">
            <render_choice>
              <response_label ident="QUE_pool13685_3_1">
                <material>
                  <mattext texttype="text/html">Application class</mattext>
                </material>
              </response_label>
              <response_label ident="QUE_pool13685_3_2">
                <material>
                  <mattext texttype="text/html">ApplicationHelper class</mattext>
                </material>
              </response_label>
              <response_label ident="QUE_pool13685_3_3">
                <material>
                  <mattext texttype="text/html">Node class</mattext>
                </material>
              </response_label>
              <response_label ident="QUE_pool13685_3_4">
                <material>
                  <mattext texttype="text/html">PacketHelper class</mattext>
                </material>
              </response_label>
            </render_choice>
          </response_lid>
        </presentation>
        <resprocessing>
          <outcomes>
            <decvar maxvalue="1.0" minvalue="0" varname="SCORE" vartype="Decimal"/>
          </outcomes>
          <respcondition continue="Yes">
              <conditionvar>
                <varequal respident="QUE_pool13685_3_RL">QUE_pool13685_3_1</varequal>
              </conditionvar>
              <displayfeedback feedbacktype="Response" linkrefid="QUE_pool13685_3_1_fb" />
          </respcondition>
          <respcondition continue="Yes">
              <conditionvar>
                <varequal respident="QUE_pool13685_3_RL">QUE_pool13685_3_2</varequal>
              </conditionvar>
              <displayfeedback feedbacktype="Response" linkrefid="QUE_pool13685_3_2_fb" />
          </respcondition>
          <respcondition continue="Yes">
              <conditionvar>
                <varequal respident="QUE_pool13685_3_RL">QUE_pool13685_3_3</varequal>
              </conditionvar>
              <displayfeedback feedbacktype="Response" linkrefid="QUE_pool13685_3_3_fb" />
          </respcondition>
          <respcondition continue="Yes">
              <conditionvar>
                <varequal respident="QUE_pool13685_3_RL">QUE_pool13685_3_4</varequal>
              </conditionvar>
              <displayfeedback feedbacktype="Response" linkrefid="QUE_pool13685_3_4_fb" />
          </respcondition>
          <respcondition continue="No">
            <conditionvar>
              <varequal case="Yes" respident="QUE_pool13685_3_RL">QUE_pool13685_3_1</varequal>
            </conditionvar>
            <setvar action="Set" varname="SCORE">100</setvar>
          </respcondition>
        </resprocessing>
        <itemfeedback ident="QUE_pool13685_3_1_fb">
          <material>
            <mattext texttype="text/html"></mattext>
          </material>
        </itemfeedback>
        <itemfeedback ident="QUE_pool13685_3_2_fb">
          <material>
            <mattext texttype="text/html"></mattext>
          </material>
        </itemfeedback>
        <itemfeedback ident="QUE_pool13685_3_3_fb">
          <material>
            <mattext texttype="text/html"></mattext>
          </material>
        </itemfeedback>
        <itemfeedback ident="QUE_pool13685_3_4_fb">
          <material>
            <mattext texttype="text/html"></mattext>
          </material>
        </itemfeedback>
      </item>
      <item ident="QUE_pool13685_4" title="MCQ16 4">
        <itemmetadata>
          <qtimetadata>
            <qtimetadatafield>
              <fieldlabel>cc_profile</fieldlabel>
              <fieldentry>cc.multiple_choice.v0p1</fieldentry>
            </qtimetadatafield>
          </qtimetadata>
        </itemmetadata>
        <presentation>
          <material>
            <mattext texttype="text/html">Which parameter in NS3 controls the channel bandwidth of a mobile device in a 3G simulation?</mattext>
          </material>
          <response_lid ident="QUE_pool13685_4_RL" rcardinality="Single">
            <render_choice>
              <response_label ident="QUE_pool13685_4_1">
                <material>
                  <mattext texttype="text/html">ChannelWidth</mattext>
                </material>
              </response_label>
              <response_label ident="QUE_pool13685_4_2">
                <material>
                  <mattext texttype="text/html">Bandwidth</mattext>
                </material>
              </response_label>
              <response_label ident="QUE_pool13685_4_3">
                <material>
                  <mattext texttype="text/html">TxRate</mattext>
                </material>
              </response_label>
              <response_label ident="QUE_pool13685_4_4">
                <material>
                  <mattext texttype="text/html">DataRate</mattext>
                </material>
              </response_label>
            </render_choice>
          </response_lid>
        </presentation>
        <resprocessing>
          <outcomes>
            <decvar maxvalue="1.0" minvalue="0" varname="SCORE" vartype="Decimal"/>
          </outcomes>
          <respcondition continue="Yes">
              <conditionvar>
                <varequal respident="QUE_pool13685_4_RL">QUE_pool13685_4_1</varequal>
              </conditionvar>
              <displayfeedback feedbacktype="Response" linkrefid="QUE_pool13685_4_1_fb" />
          </respcondition>
          <respcondition continue="Yes">
              <conditionvar>
                <varequal respident="QUE_pool13685_4_RL">QUE_pool13685_4_2</varequal>
              </conditionvar>
              <displayfeedback feedbacktype="Response" linkrefid="QUE_pool13685_4_2_fb" />
          </respcondition>
          <respcondition continue="Yes">
              <conditionvar>
                <varequal respident="QUE_pool13685_4_RL">QUE_pool13685_4_3</varequal>
              </conditionvar>
              <displayfeedback feedbacktype="Response" linkrefid="QUE_pool13685_4_3_fb" />
          </respcondition>
          <respcondition continue="Yes">
              <conditionvar>
                <varequal respident="QUE_pool13685_4_RL">QUE_pool13685_4_4</varequal>
              </conditionvar>
              <displayfeedback feedbacktype="Response" linkrefid="QUE_pool13685_4_4_fb" />
          </respcondition>
          <respcondition continue="No">
            <conditionvar>
              <varequal case="Yes" respident="QUE_pool13685_4_RL">QUE_pool13685_4_2</varequal>
            </conditionvar>
            <setvar action="Set" varname="SCORE">100</setvar>
          </respcondition>
        </resprocessing>
        <itemfeedback ident="QUE_pool13685_4_1_fb">
          <material>
            <mattext texttype="text/html"></mattext>
          </material>
        </itemfeedback>
        <itemfeedback ident="QUE_pool13685_4_2_fb">
          <material>
            <mattext texttype="text/html"></mattext>
          </material>
        </itemfeedback>
        <itemfeedback ident="QUE_pool13685_4_3_fb">
          <material>
            <mattext texttype="text/html"></mattext>
          </material>
        </itemfeedback>
        <itemfeedback ident="QUE_pool13685_4_4_fb">
          <material>
            <mattext texttype="text/html"></mattext>
          </material>
        </itemfeedback>
      </item>
      <item ident="QUE_pool13685_5" title="MCQ16 5">
        <itemmetadata>
          <qtimetadata>
            <qtimetadatafield>
              <fieldlabel>cc_profile</fieldlabel>
              <fieldentry>cc.multiple_choice.v0p1</fieldentry>
            </qtimetadatafield>
          </qtimetadata>
        </itemmetadata>
        <presentation>
          <material>
            <mattext texttype="text/html">In NS3, which class is responsible for configuring and managing the mobility of nodes in a 3G simulation?</mattext>
          </material>
          <response_lid ident="QUE_pool13685_5_RL" rcardinality="Single">
            <render_choice>
              <response_label ident="QUE_pool13685_5_1">
                <material>
                  <mattext texttype="text/html">MobilityHelper class</mattext>
                </material>
              </response_label>
              <response_label ident="QUE_pool13685_5_2">
                <material>
                  <mattext texttype="text/html">MobilityModel class</mattext>
                </material>
              </response_label>
              <response_label ident="QUE_pool13685_5_3">
                <material>
                  <mattext texttype="text/html">Node class</mattext>
                </material>
              </response_label>
              <response_label ident="QUE_pool13685_5_4">
                <material>
                  <mattext texttype="text/html">NetDevice class</mattext>
                </material>
              </response_label>
            </render_choice>
          </response_lid>
        </presentation>
        <resprocessing>
          <outcomes>
            <decvar maxvalue="1.0" minvalue="0" varname="SCORE" vartype="Decimal"/>
          </outcomes>
          <respcondition continue="Yes">
              <conditionvar>
                <varequal respident="QUE_pool13685_5_RL">QUE_pool13685_5_1</varequal>
              </conditionvar>
              <displayfeedback feedbacktype="Response" linkrefid="QUE_pool13685_5_1_fb" />
          </respcondition>
          <respcondition continue="Yes">
              <conditionvar>
                <varequal respident="QUE_pool13685_5_RL">QUE_pool13685_5_2</varequal>
              </conditionvar>
              <displayfeedback feedbacktype="Response" linkrefid="QUE_pool13685_5_2_fb" />
          </respcondition>
          <respcondition continue="Yes">
              <conditionvar>
                <varequal respident="QUE_pool13685_5_RL">QUE_pool13685_5_3</varequal>
              </conditionvar>
              <displayfeedback feedbacktype="Response" linkrefid="QUE_pool13685_5_3_fb" />
          </respcondition>
          <respcondition continue="Yes">
              <conditionvar>
                <varequal respident="QUE_pool13685_5_RL">QUE_pool13685_5_4</varequal>
              </conditionvar>
              <displayfeedback feedbacktype="Response" linkrefid="QUE_pool13685_5_4_fb" />
          </respcondition>
          <respcondition continue="No">
            <conditionvar>
              <varequal case="Yes" respident="QUE_pool13685_5_RL">QUE_pool13685_5_2</varequal>
            </conditionvar>
            <setvar action="Set" varname="SCORE">100</setvar>
          </respcondition>
        </resprocessing>
        <itemfeedback ident="QUE_pool13685_5_1_fb">
          <material>
            <mattext texttype="text/html"></mattext>
          </material>
        </itemfeedback>
        <itemfeedback ident="QUE_pool13685_5_2_fb">
          <material>
            <mattext texttype="text/html"></mattext>
          </material>
        </itemfeedback>
        <itemfeedback ident="QUE_pool13685_5_3_fb">
          <material>
            <mattext texttype="text/html"></mattext>
          </material>
        </itemfeedback>
        <itemfeedback ident="QUE_pool13685_5_4_fb">
          <material>
            <mattext texttype="text/html"></mattext>
          </material>
        </itemfeedback>
      </item>
  </objectbank>
</questestinterop>
